package com.alipay.apmobilesecuritysdk.a;

import android.content.Context;
import com.alipay.apmobilesecuritysdk.e.b;
import com.alipay.security.mobile.module.a.c;
import com.alipay.security.mobile.module.http.IUpload;
import com.alipay.security.mobile.module.http.UploadFactory;
import com.alipay.tscenter.biz.rpc.vkeydfp.request.DeviceDataReportRequest;
import java.util.HashMap;
import java.util.Map;

public class a
{
  private static final String b = a.class.getName();
  private static boolean c = false;
  private final Context a;

  public a(Context paramContext)
  {
    this.a = paramContext;
  }

  public static String a(Context paramContext)
  {
    String str1 = "";
    try
    {
      str1 = i.b();
      if (!com.alipay.security.mobile.module.a.a.a(str1))
        return str1;
      e locale = d.a(paramContext);
      if ((locale != null) && (!com.alipay.security.mobile.module.a.a.a(locale.c())))
      {
        String str2 = locale.c();
        return str2;
      }
    }
    catch (Throwable localThrowable)
    {
    }
    return str1;
  }

  private static void a(boolean paramBoolean)
  {
    monitorenter;
    try
    {
      c = paramBoolean;
      monitorexit;
      return;
    }
    finally
    {
      localObject = finally;
      monitorexit;
    }
    throw localObject;
  }

  private static boolean a()
  {
    monitorenter;
    try
    {
      boolean bool = c;
      monitorexit;
      return bool;
    }
    finally
    {
      localObject = finally;
      monitorexit;
    }
    throw localObject;
  }

  private g b(Map<String, String> paramMap)
  {
    while (true)
    {
      try
      {
        Context localContext = this.a;
        DeviceDataReportRequest localDeviceDataReportRequest = new DeviceDataReportRequest();
        String str1 = "";
        String str2 = "";
        String str3 = com.alipay.security.mobile.module.a.a.a(paramMap, "umid", "");
        e locale1 = d.b(localContext);
        if (locale1 != null)
        {
          str1 = locale1.c();
          String str4 = locale1.a();
          String str5 = locale1.d();
          str6 = str4;
          str7 = str5;
          e locale2 = d.a();
          if (locale2 == null)
            continue;
          str2 = locale2.a();
          if ((!com.alipay.security.mobile.module.a.a.a(str6)) || (!com.alipay.security.mobile.module.a.a.a(str2)))
            continue;
          str6 = com.alipay.apmobilesecuritysdk.a.a.a.b(localContext);
          str2 = com.alipay.apmobilesecuritysdk.a.a.a.a();
          localDeviceDataReportRequest.os = "android";
          localDeviceDataReportRequest.priApdid = str6;
          localDeviceDataReportRequest.pubApdid = str2;
          localDeviceDataReportRequest.token = str1;
          localDeviceDataReportRequest.umidToken = str3;
          localDeviceDataReportRequest.lastTime = str7;
          localDeviceDataReportRequest.version = "3";
          HashMap localHashMap = new HashMap();
          localHashMap.putAll(com.alipay.apmobilesecuritysdk.d.d.a(localContext, paramMap));
          localDeviceDataReportRequest.dataMap = localHashMap;
          if (localDeviceDataReportRequest.dataMap == null)
            continue;
          Map localMap1 = localDeviceDataReportRequest.dataMap;
          com.alipay.security.mobile.module.b.a.a();
          localMap1.put("AL3", com.alipay.security.mobile.module.b.a.l(localContext));
          Map localMap2 = localDeviceDataReportRequest.dataMap;
          String str8 = h.d(localContext);
          String str9 = h.c(localContext);
          if (com.alipay.security.mobile.module.a.a.a(str8))
            break label343;
          if (!com.alipay.security.mobile.module.a.a.a(str9))
            continue;
          break label343;
          localMap2.put("AA5", localObject);
          return new g(UploadFactory.create(this.a, com.alipay.apmobilesecuritysdk.b.a.b).updateStaticData(localDeviceDataReportRequest));
          com.alipay.security.mobile.module.b.a.a();
          String str10 = com.alipay.apmobilesecuritysdk.e.a.a(com.alipay.security.mobile.module.b.a.m(localContext), str9, str8);
          localObject = str10;
          continue;
        }
      }
      catch (Throwable localThrowable)
      {
        c.a(localThrowable);
        return null;
      }
      String str6 = "";
      String str7 = "";
      continue;
      label343: Object localObject = "";
    }
  }

  public static String b(Context paramContext)
  {
    String str = "";
    try
    {
      str = i.a();
      if (!com.alipay.security.mobile.module.a.a.a(str))
        return str;
      e locale = d.a(paramContext);
      if ((locale != null) && (!com.alipay.security.mobile.module.a.a.a(locale.a())))
        return locale.a();
      str = com.alipay.apmobilesecuritysdk.a.a.a.a(paramContext);
      if (com.alipay.security.mobile.module.a.a.a(str))
      {
        str = b.a(paramContext);
        boolean bool = com.alipay.security.mobile.module.a.a.a(str);
        if (!bool)
          return str;
      }
    }
    catch (Throwable localThrowable)
    {
    }
    return str;
  }

  // ERROR //
  public final String a(Map<String, String> paramMap)
  {
    // Byte code:
    //   0: aload_1
    //   1: ifnonnull +6 -> 7
    //   4: ldc 34
    //   6: areturn
    //   7: new 207	java/lang/StringBuilder
    //   10: dup
    //   11: invokespecial 208	java/lang/StringBuilder:<init>	()V
    //   14: aload_0
    //   15: getfield 28	com/alipay/apmobilesecuritysdk/a/a:a	Landroid/content/Context;
    //   18: invokevirtual 214	android/content/Context:getFilesDir	()Ljava/io/File;
    //   21: invokevirtual 219	java/io/File:getAbsolutePath	()Ljava/lang/String;
    //   24: invokevirtual 223	java/lang/StringBuilder:append	(Ljava/lang/String;)Ljava/lang/StringBuilder;
    //   27: ldc 225
    //   29: invokevirtual 223	java/lang/StringBuilder:append	(Ljava/lang/String;)Ljava/lang/StringBuilder;
    //   32: invokevirtual 228	java/lang/StringBuilder:toString	()Ljava/lang/String;
    //   35: astore 5
    //   37: getstatic 233	android/os/Build:MODEL	Ljava/lang/String;
    //   40: astore 6
    //   42: aload_0
    //   43: getfield 28	com/alipay/apmobilesecuritysdk/a/a:a	Landroid/content/Context;
    //   46: invokevirtual 237	android/content/Context:getApplicationContext	()Landroid/content/Context;
    //   49: invokevirtual 241	android/content/Context:getApplicationInfo	()Landroid/content/pm/ApplicationInfo;
    //   52: getfield 246	android/content/pm/ApplicationInfo:packageName	Ljava/lang/String;
    //   55: astore 7
    //   57: aload_1
    //   58: ldc 248
    //   60: ldc 34
    //   62: invokestatic 106	com/alipay/security/mobile/module/a/a:a	(Ljava/util/Map;Ljava/lang/String;Ljava/lang/String;)Ljava/lang/String;
    //   65: astore 8
    //   67: aload_1
    //   68: ldc 250
    //   70: ldc 34
    //   72: invokestatic 106	com/alipay/security/mobile/module/a/a:a	(Ljava/util/Map;Ljava/lang/String;Ljava/lang/String;)Ljava/lang/String;
    //   75: astore 9
    //   77: ldc 34
    //   79: astore 10
    //   81: aload_0
    //   82: getfield 28	com/alipay/apmobilesecuritysdk/a/a:a	Landroid/content/Context;
    //   85: invokestatic 48	com/alipay/apmobilesecuritysdk/a/d:a	(Landroid/content/Context;)Lcom/alipay/apmobilesecuritysdk/a/e;
    //   88: astore 11
    //   90: aload 11
    //   92: ifnull +10 -> 102
    //   95: aload 11
    //   97: invokevirtual 110	com/alipay/apmobilesecuritysdk/a/e:a	()Ljava/lang/String;
    //   100: astore 10
    //   102: new 252	com/alipay/apmobilesecuritysdk/c/a
    //   105: dup
    //   106: aload 6
    //   108: aload 7
    //   110: ldc 254
    //   112: ldc_w 256
    //   115: aload 8
    //   117: aload 9
    //   119: aload 10
    //   121: invokespecial 259	com/alipay/apmobilesecuritysdk/c/a:<init>	(Ljava/lang/String;Ljava/lang/String;Ljava/lang/String;Ljava/lang/String;Ljava/lang/String;Ljava/lang/String;Ljava/lang/String;)V
    //   124: astore 12
    //   126: invokestatic 265	java/util/Calendar:getInstance	()Ljava/util/Calendar;
    //   129: invokevirtual 269	java/util/Calendar:getTime	()Ljava/util/Date;
    //   132: astore 13
    //   134: new 271	java/text/SimpleDateFormat
    //   137: dup
    //   138: ldc_w 273
    //   141: invokespecial 276	java/text/SimpleDateFormat:<init>	(Ljava/lang/String;)V
    //   144: aload 13
    //   146: invokevirtual 280	java/text/SimpleDateFormat:format	(Ljava/util/Date;)Ljava/lang/String;
    //   149: astore 14
    //   151: aload 5
    //   153: new 207	java/lang/StringBuilder
    //   156: dup
    //   157: invokespecial 208	java/lang/StringBuilder:<init>	()V
    //   160: aload 14
    //   162: invokevirtual 223	java/lang/StringBuilder:append	(Ljava/lang/String;)Ljava/lang/StringBuilder;
    //   165: ldc_w 282
    //   168: invokevirtual 223	java/lang/StringBuilder:append	(Ljava/lang/String;)Ljava/lang/StringBuilder;
    //   171: invokevirtual 228	java/lang/StringBuilder:toString	()Ljava/lang/String;
    //   174: aload 12
    //   176: invokevirtual 283	com/alipay/apmobilesecuritysdk/c/a:toString	()Ljava/lang/String;
    //   179: invokestatic 286	com/alipay/security/mobile/module/a/c:a	(Ljava/lang/String;Ljava/lang/String;Ljava/lang/String;)V
    //   182: new 288	java/lang/Thread
    //   185: dup
    //   186: new 290	com/alipay/apmobilesecuritysdk/a/b
    //   189: dup
    //   190: aload_0
    //   191: invokespecial 293	com/alipay/apmobilesecuritysdk/a/b:<init>	(Lcom/alipay/apmobilesecuritysdk/a/a;)V
    //   194: invokespecial 296	java/lang/Thread:<init>	(Ljava/lang/Runnable;)V
    //   197: invokevirtual 299	java/lang/Thread:start	()V
    //   200: aload_1
    //   201: ldc_w 301
    //   204: ldc 34
    //   206: invokestatic 106	com/alipay/security/mobile/module/a/a:a	(Ljava/util/Map;Ljava/lang/String;Ljava/lang/String;)Ljava/lang/String;
    //   209: astore 15
    //   211: invokestatic 303	com/alipay/apmobilesecuritysdk/d/d:a	()V
    //   214: aload_0
    //   215: getfield 28	com/alipay/apmobilesecuritysdk/a/a:a	Landroid/content/Context;
    //   218: aload_1
    //   219: invokestatic 306	com/alipay/apmobilesecuritysdk/d/d:b	(Landroid/content/Context;Ljava/util/Map;)Ljava/lang/String;
    //   222: astore 16
    //   224: aload_0
    //   225: getfield 28	com/alipay/apmobilesecuritysdk/a/a:a	Landroid/content/Context;
    //   228: invokestatic 48	com/alipay/apmobilesecuritysdk/a/d:a	(Landroid/content/Context;)Lcom/alipay/apmobilesecuritysdk/a/e;
    //   231: astore 17
    //   233: aload 17
    //   235: ifnull +103 -> 338
    //   238: aload 16
    //   240: aload 17
    //   242: invokevirtual 307	com/alipay/apmobilesecuritysdk/a/e:b	()Ljava/lang/String;
    //   245: invokestatic 310	com/alipay/security/mobile/module/a/a:a	(Ljava/lang/String;Ljava/lang/String;)Z
    //   248: ifne +84 -> 332
    //   251: iconst_1
    //   252: istore 18
    //   254: aload_0
    //   255: getfield 28	com/alipay/apmobilesecuritysdk/a/a:a	Landroid/content/Context;
    //   258: invokestatic 313	com/alipay/apmobilesecuritysdk/a/i:a	(Landroid/content/Context;)Z
    //   261: istore 19
    //   263: iload 18
    //   265: ifne +79 -> 344
    //   268: iload 19
    //   270: ifeq +74 -> 344
    //   273: aload 17
    //   275: invokevirtual 52	com/alipay/apmobilesecuritysdk/a/e:c	()Ljava/lang/String;
    //   278: invokestatic 43	com/alipay/security/mobile/module/a/a:a	(Ljava/lang/String;)Z
    //   281: ifne +63 -> 344
    //   284: aload 17
    //   286: invokevirtual 52	com/alipay/apmobilesecuritysdk/a/e:c	()Ljava/lang/String;
    //   289: astore 46
    //   291: aload 46
    //   293: astore 4
    //   295: new 315	com/alipay/apmobilesecuritysdk/c/b
    //   298: dup
    //   299: aload 5
    //   301: aload_0
    //   302: getfield 28	com/alipay/apmobilesecuritysdk/a/a:a	Landroid/content/Context;
    //   305: getstatic 60	com/alipay/apmobilesecuritysdk/b/a:b	Lcom/alipay/security/mobile/module/http/UploadFactory$Mode;
    //   308: invokestatic 66	com/alipay/security/mobile/module/http/UploadFactory:create	(Landroid/content/Context;Lcom/alipay/security/mobile/module/http/UploadFactory$Mode;)Lcom/alipay/security/mobile/module/http/IUpload;
    //   311: invokespecial 318	com/alipay/apmobilesecuritysdk/c/b:<init>	(Ljava/lang/String;Lcom/alipay/security/mobile/module/http/IUpload;)V
    //   314: aload_0
    //   315: getfield 28	com/alipay/apmobilesecuritysdk/a/a:a	Landroid/content/Context;
    //   318: invokevirtual 320	com/alipay/apmobilesecuritysdk/c/b:a	(Landroid/content/Context;)V
    //   321: aload 4
    //   323: areturn
    //   324: astore_3
    //   325: aload_3
    //   326: invokestatic 97	com/alipay/security/mobile/module/a/c:a	(Ljava/lang/Throwable;)V
    //   329: aload 4
    //   331: areturn
    //   332: iconst_0
    //   333: istore 18
    //   335: goto -81 -> 254
    //   338: iconst_1
    //   339: istore 18
    //   341: goto -87 -> 254
    //   344: aload_0
    //   345: aload_1
    //   346: invokespecial 322	com/alipay/apmobilesecuritysdk/a/a:b	(Ljava/util/Map;)Lcom/alipay/apmobilesecuritysdk/a/g;
    //   349: astore 20
    //   351: aload 20
    //   353: ifnull +325 -> 678
    //   356: aload 20
    //   358: invokevirtual 323	com/alipay/apmobilesecuritysdk/a/g:a	()Z
    //   361: ifeq +317 -> 678
    //   364: getstatic 20	com/alipay/apmobilesecuritysdk/a/a:b	Ljava/lang/String;
    //   367: pop
    //   368: aload_0
    //   369: getfield 28	com/alipay/apmobilesecuritysdk/a/a:a	Landroid/content/Context;
    //   372: astore 22
    //   374: aload 20
    //   376: invokevirtual 326	com/alipay/apmobilesecuritysdk/a/g:f	()Z
    //   379: istore 23
    //   381: aload 22
    //   383: ldc_w 328
    //   386: iconst_0
    //   387: invokevirtual 332	android/content/Context:getSharedPreferences	(Ljava/lang/String;I)Landroid/content/SharedPreferences;
    //   390: invokeinterface 338 1 0
    //   395: astore 41
    //   397: aload 41
    //   399: ifnull +40 -> 439
    //   402: iload 23
    //   404: ifeq +238 -> 642
    //   407: invokestatic 341	com/alipay/security/mobile/module/a/a/c:a	()Ljava/lang/String;
    //   410: ldc_w 343
    //   413: invokestatic 346	com/alipay/security/mobile/module/a/a/c:a	(Ljava/lang/String;Ljava/lang/String;)Ljava/lang/String;
    //   416: astore 42
    //   418: aload 41
    //   420: ldc_w 348
    //   423: aload 42
    //   425: invokeinterface 354 3 0
    //   430: pop
    //   431: aload 41
    //   433: invokeinterface 357 1 0
    //   438: pop
    //   439: aload_0
    //   440: getfield 28	com/alipay/apmobilesecuritysdk/a/a:a	Landroid/content/Context;
    //   443: invokestatic 178	com/alipay/apmobilesecuritysdk/a/h:d	(Landroid/content/Context;)Ljava/lang/String;
    //   446: astore 25
    //   448: aload 20
    //   450: invokevirtual 360	com/alipay/apmobilesecuritysdk/a/g:g	()Ljava/lang/String;
    //   453: invokestatic 43	com/alipay/security/mobile/module/a/a:a	(Ljava/lang/String;)Z
    //   456: ifne +54 -> 510
    //   459: aload 25
    //   461: aload 20
    //   463: invokevirtual 360	com/alipay/apmobilesecuritysdk/a/g:g	()Ljava/lang/String;
    //   466: invokestatic 310	com/alipay/security/mobile/module/a/a:a	(Ljava/lang/String;Ljava/lang/String;)Z
    //   469: ifne +41 -> 510
    //   472: aload 20
    //   474: invokevirtual 361	com/alipay/apmobilesecuritysdk/a/g:c	()Ljava/lang/String;
    //   477: astore 38
    //   479: invokestatic 362	com/alipay/apmobilesecuritysdk/a/a:a	()Z
    //   482: ifne +28 -> 510
    //   485: iconst_1
    //   486: invokestatic 83	com/alipay/apmobilesecuritysdk/a/a:a	(Z)V
    //   489: new 364	com/alipay/apmobilesecuritysdk/a/c
    //   492: dup
    //   493: aload_0
    //   494: aload 15
    //   496: aload 38
    //   498: ldc 34
    //   500: invokespecial 366	com/alipay/apmobilesecuritysdk/a/c:<init>	(Lcom/alipay/apmobilesecuritysdk/a/a;Ljava/lang/String;Ljava/lang/String;Ljava/lang/String;)V
    //   503: invokevirtual 299	java/lang/Thread:start	()V
    //   506: iconst_0
    //   507: invokestatic 83	com/alipay/apmobilesecuritysdk/a/a:a	(Z)V
    //   510: aload_0
    //   511: getfield 28	com/alipay/apmobilesecuritysdk/a/a:a	Landroid/content/Context;
    //   514: aload_1
    //   515: invokestatic 306	com/alipay/apmobilesecuritysdk/d/d:b	(Landroid/content/Context;Ljava/util/Map;)Ljava/lang/String;
    //   518: astore 26
    //   520: aload 20
    //   522: ifnull +106 -> 628
    //   525: new 50	com/alipay/apmobilesecuritysdk/a/e
    //   528: dup
    //   529: aload 20
    //   531: aload 26
    //   533: invokespecial 369	com/alipay/apmobilesecuritysdk/a/e:<init>	(Lcom/alipay/apmobilesecuritysdk/a/g;Ljava/lang/String;)V
    //   536: astore 27
    //   538: aload_0
    //   539: getfield 28	com/alipay/apmobilesecuritysdk/a/a:a	Landroid/content/Context;
    //   542: aload 27
    //   544: invokestatic 372	com/alipay/apmobilesecuritysdk/a/d:a	(Landroid/content/Context;Lcom/alipay/apmobilesecuritysdk/a/e;)V
    //   547: aload 27
    //   549: invokestatic 375	com/alipay/apmobilesecuritysdk/a/i:a	(Lcom/alipay/apmobilesecuritysdk/a/e;)V
    //   552: aload_0
    //   553: getfield 28	com/alipay/apmobilesecuritysdk/a/a:a	Landroid/content/Context;
    //   556: pop
    //   557: aload 27
    //   559: invokestatic 376	com/alipay/apmobilesecuritysdk/a/a/a:a	(Lcom/alipay/apmobilesecuritysdk/a/e;)V
    //   562: aload_0
    //   563: getfield 28	com/alipay/apmobilesecuritysdk/a/a:a	Landroid/content/Context;
    //   566: astore 29
    //   568: invokestatic 382	java/lang/System:currentTimeMillis	()J
    //   571: lstore 30
    //   573: aload 29
    //   575: ldc_w 328
    //   578: iconst_0
    //   579: invokevirtual 332	android/content/Context:getSharedPreferences	(Ljava/lang/String;I)Landroid/content/SharedPreferences;
    //   582: invokeinterface 338 1 0
    //   587: astore 34
    //   589: aload 34
    //   591: ifnull +37 -> 628
    //   594: lload 30
    //   596: invokestatic 388	java/lang/String:valueOf	(J)Ljava/lang/String;
    //   599: astore 35
    //   601: aload 34
    //   603: ldc_w 390
    //   606: invokestatic 341	com/alipay/security/mobile/module/a/a/c:a	()Ljava/lang/String;
    //   609: aload 35
    //   611: invokestatic 346	com/alipay/security/mobile/module/a/a/c:a	(Ljava/lang/String;Ljava/lang/String;)Ljava/lang/String;
    //   614: invokeinterface 354 3 0
    //   619: pop
    //   620: aload 34
    //   622: invokeinterface 357 1 0
    //   627: pop
    //   628: aload 20
    //   630: invokevirtual 361	com/alipay/apmobilesecuritysdk/a/g:c	()Ljava/lang/String;
    //   633: astore 33
    //   635: aload 33
    //   637: astore 4
    //   639: goto -344 -> 295
    //   642: invokestatic 341	com/alipay/security/mobile/module/a/a/c:a	()Ljava/lang/String;
    //   645: ldc_w 392
    //   648: invokestatic 346	com/alipay/security/mobile/module/a/a/c:a	(Ljava/lang/String;Ljava/lang/String;)Ljava/lang/String;
    //   651: astore 45
    //   653: aload 45
    //   655: astore 42
    //   657: goto -239 -> 418
    //   660: astore 40
    //   662: iconst_0
    //   663: invokestatic 83	com/alipay/apmobilesecuritysdk/a/a:a	(Z)V
    //   666: goto -156 -> 510
    //   669: astore 39
    //   671: iconst_0
    //   672: invokestatic 83	com/alipay/apmobilesecuritysdk/a/a:a	(Z)V
    //   675: aload 39
    //   677: athrow
    //   678: aload 20
    //   680: ifnull +53 -> 733
    //   683: new 207	java/lang/StringBuilder
    //   686: dup
    //   687: ldc_w 394
    //   690: invokespecial 395	java/lang/StringBuilder:<init>	(Ljava/lang/String;)V
    //   693: aload 20
    //   695: invokevirtual 398	com/alipay/apmobilesecuritysdk/a/g:e	()Ljava/lang/String;
    //   698: invokevirtual 223	java/lang/StringBuilder:append	(Ljava/lang/String;)Ljava/lang/StringBuilder;
    //   701: invokevirtual 228	java/lang/StringBuilder:toString	()Ljava/lang/String;
    //   704: invokestatic 400	com/alipay/security/mobile/module/a/c:a	(Ljava/lang/String;)V
    //   707: aload 17
    //   709: ifnull +33 -> 742
    //   712: aload 17
    //   714: invokevirtual 52	com/alipay/apmobilesecuritysdk/a/e:c	()Ljava/lang/String;
    //   717: invokestatic 43	com/alipay/security/mobile/module/a/a:a	(Ljava/lang/String;)Z
    //   720: ifne +22 -> 742
    //   723: aload 17
    //   725: invokevirtual 52	com/alipay/apmobilesecuritysdk/a/e:c	()Ljava/lang/String;
    //   728: astore 4
    //   730: goto -435 -> 295
    //   733: ldc_w 402
    //   736: invokestatic 400	com/alipay/security/mobile/module/a/c:a	(Ljava/lang/String;)V
    //   739: goto -32 -> 707
    //   742: ldc 34
    //   744: astore 4
    //   746: goto -451 -> 295
    //   749: astore 32
    //   751: goto -123 -> 628
    //   754: astore 24
    //   756: goto -317 -> 439
    //   759: astore_2
    //   760: aload_2
    //   761: astore_3
    //   762: ldc 34
    //   764: astore 4
    //   766: goto -441 -> 325
    //
    // Exception table:
    //   from	to	target	type
    //   295	321	324	java/lang/Throwable
    //   489	506	660	java/lang/Throwable
    //   489	506	669	finally
    //   573	589	749	java/lang/Throwable
    //   594	628	749	java/lang/Throwable
    //   381	397	754	java/lang/Throwable
    //   407	418	754	java/lang/Throwable
    //   418	439	754	java/lang/Throwable
    //   642	653	754	java/lang/Throwable
    //   7	77	759	java/lang/Throwable
    //   81	90	759	java/lang/Throwable
    //   95	102	759	java/lang/Throwable
    //   102	233	759	java/lang/Throwable
    //   238	251	759	java/lang/Throwable
    //   254	263	759	java/lang/Throwable
    //   273	291	759	java/lang/Throwable
    //   344	351	759	java/lang/Throwable
    //   356	381	759	java/lang/Throwable
    //   439	489	759	java/lang/Throwable
    //   506	510	759	java/lang/Throwable
    //   510	520	759	java/lang/Throwable
    //   525	573	759	java/lang/Throwable
    //   628	635	759	java/lang/Throwable
    //   662	666	759	java/lang/Throwable
    //   671	678	759	java/lang/Throwable
    //   683	707	759	java/lang/Throwable
    //   712	730	759	java/lang/Throwable
    //   733	739	759	java/lang/Throwable
  }
}

/* Location:           C:\Androidnixiangzhushou\zikao_classes_dex2jar.jar
 * Qualified Name:     com.alipay.apmobilesecuritysdk.a.a
 * JD-Core Version:    0.6.0
 */