package com.umeng.socialize.b;

import com.umeng.socialize.b.a.f;
import com.umeng.socialize.bean.az;
import org.json.JSONObject;

public class j extends f
{
  public az a;

  public j(JSONObject paramJSONObject)
  {
    super(paramJSONObject);
  }

  // ERROR //
  public void a()
  {
    // Byte code:
    //   0: aload_0
    //   1: getfield 19	com/umeng/socialize/b/j:l	Lorg/json/JSONObject;
    //   4: astore_1
    //   5: aload_1
    //   6: ifnonnull +12 -> 18
    //   9: getstatic 23	com/umeng/socialize/b/a/f:k	Ljava/lang/String;
    //   12: ldc 25
    //   14: invokestatic 31	com/umeng/socialize/utils/i:b	(Ljava/lang/String;Ljava/lang/String;)V
    //   17: return
    //   18: aload_0
    //   19: new 33	com/umeng/socialize/bean/az
    //   22: dup
    //   23: invokespecial 35	com/umeng/socialize/bean/az:<init>	()V
    //   26: putfield 37	com/umeng/socialize/b/j:a	Lcom/umeng/socialize/bean/az;
    //   29: aload_1
    //   30: ldc 39
    //   32: invokevirtual 45	org/json/JSONObject:has	(Ljava/lang/String;)Z
    //   35: ifeq +23 -> 58
    //   38: aload_1
    //   39: ldc 39
    //   41: invokevirtual 49	org/json/JSONObject:getString	(Ljava/lang/String;)Ljava/lang/String;
    //   44: astore 33
    //   46: aload_0
    //   47: getfield 37	com/umeng/socialize/b/j:a	Lcom/umeng/socialize/bean/az;
    //   50: aload 33
    //   52: invokestatic 54	com/umeng/socialize/bean/p:a	(Ljava/lang/String;)Lcom/umeng/socialize/bean/p;
    //   55: putfield 57	com/umeng/socialize/bean/az:b	Lcom/umeng/socialize/bean/p;
    //   58: aload_1
    //   59: ldc 59
    //   61: invokevirtual 45	org/json/JSONObject:has	(Ljava/lang/String;)Z
    //   64: ifeq +207 -> 271
    //   67: new 61	java/util/ArrayList
    //   70: dup
    //   71: invokespecial 62	java/util/ArrayList:<init>	()V
    //   74: astore 19
    //   76: aload_1
    //   77: ldc 59
    //   79: invokevirtual 66	org/json/JSONObject:getJSONObject	(Ljava/lang/String;)Lorg/json/JSONObject;
    //   82: astore 20
    //   84: aload 20
    //   86: invokevirtual 70	org/json/JSONObject:keys	()Ljava/util/Iterator;
    //   89: astore 21
    //   91: aload 21
    //   93: invokeinterface 76 1 0
    //   98: ifeq +446 -> 544
    //   101: aload 21
    //   103: invokeinterface 80 1 0
    //   108: invokevirtual 86	java/lang/Object:toString	()Ljava/lang/String;
    //   111: astore 22
    //   113: aload 20
    //   115: aload 22
    //   117: invokevirtual 66	org/json/JSONObject:getJSONObject	(Ljava/lang/String;)Lorg/json/JSONObject;
    //   120: astore 23
    //   122: aload 23
    //   124: ldc 88
    //   126: ldc 90
    //   128: invokevirtual 94	org/json/JSONObject:optString	(Ljava/lang/String;Ljava/lang/String;)Ljava/lang/String;
    //   131: astore 24
    //   133: aload 23
    //   135: ldc 96
    //   137: ldc 90
    //   139: invokevirtual 94	org/json/JSONObject:optString	(Ljava/lang/String;Ljava/lang/String;)Ljava/lang/String;
    //   142: astore 25
    //   144: aload 23
    //   146: ldc 98
    //   148: ldc 90
    //   150: invokevirtual 94	org/json/JSONObject:optString	(Ljava/lang/String;Ljava/lang/String;)Ljava/lang/String;
    //   153: astore 26
    //   155: aload 23
    //   157: ldc 100
    //   159: iconst_0
    //   160: invokevirtual 104	org/json/JSONObject:optInt	(Ljava/lang/String;I)I
    //   163: istore 27
    //   165: aload 23
    //   167: ldc 106
    //   169: ldc 90
    //   171: invokevirtual 94	org/json/JSONObject:optString	(Ljava/lang/String;Ljava/lang/String;)Ljava/lang/String;
    //   174: astore 28
    //   176: aload 23
    //   178: ldc 108
    //   180: ldc 90
    //   182: invokevirtual 94	org/json/JSONObject:optString	(Ljava/lang/String;Ljava/lang/String;)Ljava/lang/String;
    //   185: astore 29
    //   187: aload 23
    //   189: ldc 110
    //   191: ldc 90
    //   193: invokevirtual 94	org/json/JSONObject:optString	(Ljava/lang/String;Ljava/lang/String;)Ljava/lang/String;
    //   196: astore 30
    //   198: new 112	com/umeng/socialize/bean/av
    //   201: dup
    //   202: aload 24
    //   204: iload 27
    //   206: invokestatic 118	java/lang/String:valueOf	(I)Ljava/lang/String;
    //   209: invokestatic 123	com/umeng/socialize/bean/c:a	(Ljava/lang/String;)Lcom/umeng/socialize/bean/c;
    //   212: aload 25
    //   214: aload 26
    //   216: invokespecial 126	com/umeng/socialize/bean/av:<init>	(Ljava/lang/String;Lcom/umeng/socialize/bean/c;Ljava/lang/String;Ljava/lang/String;)V
    //   219: astore 31
    //   221: aload 31
    //   223: aload 22
    //   225: invokevirtual 129	com/umeng/socialize/bean/av:b	(Ljava/lang/String;)V
    //   228: aload 31
    //   230: aload 28
    //   232: invokevirtual 131	com/umeng/socialize/bean/av:a	(Ljava/lang/String;)V
    //   235: aload 19
    //   237: aload 31
    //   239: invokeinterface 137 2 0
    //   244: pop
    //   245: aload 31
    //   247: aload 29
    //   249: invokevirtual 140	com/umeng/socialize/bean/av:g	(Ljava/lang/String;)V
    //   252: aload 31
    //   254: aload 30
    //   256: invokevirtual 143	com/umeng/socialize/bean/av:f	(Ljava/lang/String;)V
    //   259: goto -168 -> 91
    //   262: astore_3
    //   263: getstatic 144	com/umeng/socialize/b/j:k	Ljava/lang/String;
    //   266: ldc 146
    //   268: invokestatic 148	com/umeng/socialize/utils/i:a	(Ljava/lang/String;Ljava/lang/String;)V
    //   271: aload_1
    //   272: ldc 150
    //   274: invokevirtual 45	org/json/JSONObject:has	(Ljava/lang/String;)Z
    //   277: ifeq +185 -> 462
    //   280: aload_1
    //   281: ldc 150
    //   283: invokevirtual 66	org/json/JSONObject:getJSONObject	(Ljava/lang/String;)Lorg/json/JSONObject;
    //   286: astore 7
    //   288: aload 7
    //   290: invokevirtual 70	org/json/JSONObject:keys	()Ljava/util/Iterator;
    //   293: astore 8
    //   295: aload 8
    //   297: invokeinterface 76 1 0
    //   302: ifeq +160 -> 462
    //   305: aload 8
    //   307: invokeinterface 80 1 0
    //   312: invokevirtual 86	java/lang/Object:toString	()Ljava/lang/String;
    //   315: astore 9
    //   317: aload 7
    //   319: aload 9
    //   321: invokevirtual 66	org/json/JSONObject:getJSONObject	(Ljava/lang/String;)Lorg/json/JSONObject;
    //   324: astore 10
    //   326: aload 10
    //   328: ldc 88
    //   330: ldc 90
    //   332: invokevirtual 94	org/json/JSONObject:optString	(Ljava/lang/String;Ljava/lang/String;)Ljava/lang/String;
    //   335: astore 11
    //   337: aload 10
    //   339: ldc 96
    //   341: ldc 90
    //   343: invokevirtual 94	org/json/JSONObject:optString	(Ljava/lang/String;Ljava/lang/String;)Ljava/lang/String;
    //   346: astore 12
    //   348: aload 10
    //   350: ldc 98
    //   352: ldc 90
    //   354: invokevirtual 94	org/json/JSONObject:optString	(Ljava/lang/String;Ljava/lang/String;)Ljava/lang/String;
    //   357: astore 13
    //   359: aload 10
    //   361: ldc 106
    //   363: ldc 90
    //   365: invokevirtual 94	org/json/JSONObject:optString	(Ljava/lang/String;Ljava/lang/String;)Ljava/lang/String;
    //   368: astore 14
    //   370: aload 10
    //   372: ldc 100
    //   374: iconst_0
    //   375: invokevirtual 104	org/json/JSONObject:optInt	(Ljava/lang/String;I)I
    //   378: istore 15
    //   380: aload 10
    //   382: ldc 108
    //   384: ldc 90
    //   386: invokevirtual 94	org/json/JSONObject:optString	(Ljava/lang/String;Ljava/lang/String;)Ljava/lang/String;
    //   389: astore 16
    //   391: aload 10
    //   393: ldc 110
    //   395: ldc 90
    //   397: invokevirtual 94	org/json/JSONObject:optString	(Ljava/lang/String;Ljava/lang/String;)Ljava/lang/String;
    //   400: astore 17
    //   402: new 112	com/umeng/socialize/bean/av
    //   405: dup
    //   406: aload 11
    //   408: iload 15
    //   410: invokestatic 118	java/lang/String:valueOf	(I)Ljava/lang/String;
    //   413: invokestatic 123	com/umeng/socialize/bean/c:a	(Ljava/lang/String;)Lcom/umeng/socialize/bean/c;
    //   416: aload 12
    //   418: aload 13
    //   420: invokespecial 126	com/umeng/socialize/bean/av:<init>	(Ljava/lang/String;Lcom/umeng/socialize/bean/c;Ljava/lang/String;Ljava/lang/String;)V
    //   423: astore 18
    //   425: aload 18
    //   427: aload 9
    //   429: invokevirtual 129	com/umeng/socialize/bean/av:b	(Ljava/lang/String;)V
    //   432: aload 18
    //   434: aload 14
    //   436: invokevirtual 131	com/umeng/socialize/bean/av:a	(Ljava/lang/String;)V
    //   439: aload_0
    //   440: getfield 37	com/umeng/socialize/b/j:a	Lcom/umeng/socialize/bean/az;
    //   443: aload 18
    //   445: putfield 154	com/umeng/socialize/bean/az:c	Lcom/umeng/socialize/bean/av;
    //   448: aload 18
    //   450: aload 16
    //   452: invokevirtual 140	com/umeng/socialize/bean/av:g	(Ljava/lang/String;)V
    //   455: aload 18
    //   457: aload 17
    //   459: invokevirtual 143	com/umeng/socialize/bean/av:f	(Ljava/lang/String;)V
    //   462: aload_0
    //   463: getfield 37	com/umeng/socialize/b/j:a	Lcom/umeng/socialize/bean/az;
    //   466: getfield 154	com/umeng/socialize/bean/az:c	Lcom/umeng/socialize/bean/av;
    //   469: astore 5
    //   471: aload 5
    //   473: ifnonnull -456 -> 17
    //   476: aload_1
    //   477: ldc 88
    //   479: invokevirtual 45	org/json/JSONObject:has	(Ljava/lang/String;)Z
    //   482: ifeq -465 -> 17
    //   485: aload_1
    //   486: ldc 88
    //   488: ldc 90
    //   490: invokevirtual 94	org/json/JSONObject:optString	(Ljava/lang/String;Ljava/lang/String;)Ljava/lang/String;
    //   493: putstatic 159	com/umeng/socialize/common/r:h	Ljava/lang/String;
    //   496: return
    //   497: astore 6
    //   499: getstatic 144	com/umeng/socialize/b/j:k	Ljava/lang/String;
    //   502: ldc 161
    //   504: invokestatic 148	com/umeng/socialize/utils/i:a	(Ljava/lang/String;Ljava/lang/String;)V
    //   507: return
    //   508: astore_2
    //   509: getstatic 144	com/umeng/socialize/b/j:k	Ljava/lang/String;
    //   512: new 163	java/lang/StringBuilder
    //   515: dup
    //   516: invokespecial 164	java/lang/StringBuilder:<init>	()V
    //   519: ldc 166
    //   521: invokevirtual 170	java/lang/StringBuilder:append	(Ljava/lang/String;)Ljava/lang/StringBuilder;
    //   524: aload_1
    //   525: invokevirtual 171	org/json/JSONObject:toString	()Ljava/lang/String;
    //   528: invokevirtual 170	java/lang/StringBuilder:append	(Ljava/lang/String;)Ljava/lang/StringBuilder;
    //   531: ldc 173
    //   533: invokevirtual 170	java/lang/StringBuilder:append	(Ljava/lang/String;)Ljava/lang/StringBuilder;
    //   536: invokevirtual 174	java/lang/StringBuilder:toString	()Ljava/lang/String;
    //   539: aload_2
    //   540: invokestatic 177	com/umeng/socialize/utils/i:b	(Ljava/lang/String;Ljava/lang/String;Ljava/lang/Exception;)V
    //   543: return
    //   544: aload_0
    //   545: getfield 37	com/umeng/socialize/b/j:a	Lcom/umeng/socialize/bean/az;
    //   548: aload 19
    //   550: putfield 180	com/umeng/socialize/bean/az:a	Ljava/util/List;
    //   553: goto -282 -> 271
    //   556: astore 4
    //   558: getstatic 144	com/umeng/socialize/b/j:k	Ljava/lang/String;
    //   561: ldc 161
    //   563: invokestatic 148	com/umeng/socialize/utils/i:a	(Ljava/lang/String;Ljava/lang/String;)V
    //   566: goto -104 -> 462
    //
    // Exception table:
    //   from	to	target	type
    //   58	91	262	org/json/JSONException
    //   91	259	262	org/json/JSONException
    //   544	553	262	org/json/JSONException
    //   476	496	497	java/lang/Exception
    //   18	58	508	org/json/JSONException
    //   263	271	508	org/json/JSONException
    //   462	471	508	org/json/JSONException
    //   476	496	508	org/json/JSONException
    //   499	507	508	org/json/JSONException
    //   558	566	508	org/json/JSONException
    //   271	462	556	org/json/JSONException
  }
}

/* Location:           C:\Androidnixiangzhushou\zikao_classes_dex2jar.jar
 * Qualified Name:     com.umeng.socialize.b.j
 * JD-Core Version:    0.6.0
 */