package com.gensee.net;

class AbsRtAction$2
  implements Runnable
{
  // ERROR //
  public void run()
  {
    // Byte code:
    //   0: aconst_null
    //   1: astore_1
    //   2: aload_0
    //   3: getfield 17	com/gensee/net/AbsRtAction$2:this$0	Lcom/gensee/net/AbsRtAction;
    //   6: getfield 45	com/gensee/net/AbsRtAction:mHttpHandler	Lcom/gensee/net/AbsRtHandler;
    //   9: invokevirtual 51	com/gensee/net/AbsRtHandler:is3GOrWifi	()Z
    //   12: ifne +17 -> 29
    //   15: aload_0
    //   16: getfield 19	com/gensee/net/AbsRtAction$2:val$response	Lcom/gensee/net/AbsRtAction$Response;
    //   19: bipush 152
    //   21: ldc 53
    //   23: invokeinterface 59 3 0
    //   28: return
    //   29: ldc 61
    //   31: new 63	java/lang/StringBuilder
    //   34: dup
    //   35: ldc 65
    //   37: invokespecial 68	java/lang/StringBuilder:<init>	(Ljava/lang/String;)V
    //   40: aload_0
    //   41: getfield 21	com/gensee/net/AbsRtAction$2:val$strUrl	Ljava/lang/String;
    //   44: invokevirtual 72	java/lang/StringBuilder:append	(Ljava/lang/String;)Ljava/lang/StringBuilder;
    //   47: ldc 74
    //   49: invokevirtual 72	java/lang/StringBuilder:append	(Ljava/lang/String;)Ljava/lang/StringBuilder;
    //   52: aload_0
    //   53: getfield 23	com/gensee/net/AbsRtAction$2:val$param	Ljava/lang/String;
    //   56: invokevirtual 72	java/lang/StringBuilder:append	(Ljava/lang/String;)Ljava/lang/StringBuilder;
    //   59: invokevirtual 78	java/lang/StringBuilder:toString	()Ljava/lang/String;
    //   62: invokestatic 84	com/gensee/utils/GenseeLog:d	(Ljava/lang/String;Ljava/lang/String;)V
    //   65: new 86	java/net/URL
    //   68: dup
    //   69: aload_0
    //   70: getfield 21	com/gensee/net/AbsRtAction$2:val$strUrl	Ljava/lang/String;
    //   73: invokespecial 87	java/net/URL:<init>	(Ljava/lang/String;)V
    //   76: invokevirtual 91	java/net/URL:openConnection	()Ljava/net/URLConnection;
    //   79: checkcast 93	java/net/HttpURLConnection
    //   82: astore 18
    //   84: aload 18
    //   86: iconst_1
    //   87: invokevirtual 97	java/net/HttpURLConnection:setDoInput	(Z)V
    //   90: aload 18
    //   92: iconst_1
    //   93: invokevirtual 100	java/net/HttpURLConnection:setDoOutput	(Z)V
    //   96: aload 18
    //   98: sipush 30000
    //   101: invokevirtual 104	java/net/HttpURLConnection:setConnectTimeout	(I)V
    //   104: aload 18
    //   106: ldc 106
    //   108: invokevirtual 109	java/net/HttpURLConnection:setRequestMethod	(Ljava/lang/String;)V
    //   111: aload 18
    //   113: ldc 111
    //   115: ldc 113
    //   117: invokevirtual 116	java/net/HttpURLConnection:setRequestProperty	(Ljava/lang/String;Ljava/lang/String;)V
    //   120: aload 18
    //   122: ldc 118
    //   124: ldc 120
    //   126: invokevirtual 116	java/net/HttpURLConnection:setRequestProperty	(Ljava/lang/String;Ljava/lang/String;)V
    //   129: new 122	java/io/DataOutputStream
    //   132: dup
    //   133: aload 18
    //   135: invokevirtual 126	java/net/HttpURLConnection:getOutputStream	()Ljava/io/OutputStream;
    //   138: invokespecial 129	java/io/DataOutputStream:<init>	(Ljava/io/OutputStream;)V
    //   141: astore 32
    //   143: aload 32
    //   145: aload_0
    //   146: getfield 23	com/gensee/net/AbsRtAction$2:val$param	Ljava/lang/String;
    //   149: ldc 120
    //   151: invokevirtual 135	java/lang/String:getBytes	(Ljava/lang/String;)[B
    //   154: invokevirtual 139	java/io/DataOutputStream:write	([B)V
    //   157: aload 32
    //   159: invokevirtual 142	java/io/DataOutputStream:flush	()V
    //   162: aload 32
    //   164: invokevirtual 145	java/io/DataOutputStream:close	()V
    //   167: aload 18
    //   169: invokevirtual 149	java/net/HttpURLConnection:getResponseCode	()I
    //   172: sipush 200
    //   175: if_icmpne +221 -> 396
    //   178: new 151	java/io/InputStreamReader
    //   181: dup
    //   182: aload 18
    //   184: invokevirtual 155	java/net/HttpURLConnection:getInputStream	()Ljava/io/InputStream;
    //   187: invokespecial 158	java/io/InputStreamReader:<init>	(Ljava/io/InputStream;)V
    //   190: astore 33
    //   192: new 160	java/io/BufferedReader
    //   195: dup
    //   196: aload 33
    //   198: invokespecial 163	java/io/BufferedReader:<init>	(Ljava/io/Reader;)V
    //   201: astore 34
    //   203: new 165	java/lang/StringBuffer
    //   206: dup
    //   207: invokespecial 166	java/lang/StringBuffer:<init>	()V
    //   210: astore 35
    //   212: aload 34
    //   214: invokevirtual 169	java/io/BufferedReader:readLine	()Ljava/lang/String;
    //   217: astore 42
    //   219: aload 42
    //   221: ifnonnull +97 -> 318
    //   224: aload 35
    //   226: invokevirtual 170	java/lang/StringBuffer:toString	()Ljava/lang/String;
    //   229: astore 43
    //   231: aload 43
    //   233: astore 44
    //   235: ldc 172
    //   237: new 63	java/lang/StringBuilder
    //   240: dup
    //   241: ldc 65
    //   243: invokespecial 68	java/lang/StringBuilder:<init>	(Ljava/lang/String;)V
    //   246: aload_0
    //   247: getfield 21	com/gensee/net/AbsRtAction$2:val$strUrl	Ljava/lang/String;
    //   250: invokevirtual 72	java/lang/StringBuilder:append	(Ljava/lang/String;)Ljava/lang/StringBuilder;
    //   253: ldc 174
    //   255: invokevirtual 72	java/lang/StringBuilder:append	(Ljava/lang/String;)Ljava/lang/StringBuilder;
    //   258: aload_0
    //   259: getfield 23	com/gensee/net/AbsRtAction$2:val$param	Ljava/lang/String;
    //   262: invokevirtual 72	java/lang/StringBuilder:append	(Ljava/lang/String;)Ljava/lang/StringBuilder;
    //   265: ldc 176
    //   267: invokevirtual 72	java/lang/StringBuilder:append	(Ljava/lang/String;)Ljava/lang/StringBuilder;
    //   270: aload 44
    //   272: invokevirtual 72	java/lang/StringBuilder:append	(Ljava/lang/String;)Ljava/lang/StringBuilder;
    //   275: invokevirtual 78	java/lang/StringBuilder:toString	()Ljava/lang/String;
    //   278: invokestatic 84	com/gensee/utils/GenseeLog:d	(Ljava/lang/String;Ljava/lang/String;)V
    //   281: aload 18
    //   283: ifnull +8 -> 291
    //   286: aload 18
    //   288: invokevirtual 179	java/net/HttpURLConnection:disconnect	()V
    //   291: aload 33
    //   293: ifnull +8 -> 301
    //   296: aload 33
    //   298: invokevirtual 180	java/io/InputStreamReader:close	()V
    //   301: aload 44
    //   303: ifnull -275 -> 28
    //   306: aload_0
    //   307: getfield 19	com/gensee/net/AbsRtAction$2:val$response	Lcom/gensee/net/AbsRtAction$Response;
    //   310: aload 44
    //   312: invokeinterface 183 2 0
    //   317: return
    //   318: aload 35
    //   320: aload 42
    //   322: invokevirtual 186	java/lang/StringBuffer:append	(Ljava/lang/String;)Ljava/lang/StringBuffer;
    //   325: pop
    //   326: goto -114 -> 212
    //   329: astore 41
    //   331: aload 33
    //   333: astore_3
    //   334: aconst_null
    //   335: astore 4
    //   337: aload 18
    //   339: astore 5
    //   341: aload 41
    //   343: astore_2
    //   344: aload_0
    //   345: getfield 19	com/gensee/net/AbsRtAction$2:val$response	Lcom/gensee/net/AbsRtAction$Response;
    //   348: bipush 156
    //   350: ldc 53
    //   352: invokeinterface 59 3 0
    //   357: aload_2
    //   358: invokestatic 190	com/gensee/utils/GenseeLog:e	(Ljava/lang/Exception;)V
    //   361: aload 5
    //   363: ifnull +8 -> 371
    //   366: aload 5
    //   368: invokevirtual 179	java/net/HttpURLConnection:disconnect	()V
    //   371: aload_3
    //   372: ifnull +7 -> 379
    //   375: aload_3
    //   376: invokevirtual 180	java/io/InputStreamReader:close	()V
    //   379: aload 4
    //   381: ifnull -353 -> 28
    //   384: aload_0
    //   385: getfield 19	com/gensee/net/AbsRtAction$2:val$response	Lcom/gensee/net/AbsRtAction$Response;
    //   388: aload 4
    //   390: invokeinterface 183 2 0
    //   395: return
    //   396: aload_0
    //   397: getfield 19	com/gensee/net/AbsRtAction$2:val$response	Lcom/gensee/net/AbsRtAction$Response;
    //   400: bipush 156
    //   402: ldc 53
    //   404: invokeinterface 59 3 0
    //   409: aconst_null
    //   410: astore 33
    //   412: aconst_null
    //   413: astore 44
    //   415: goto -134 -> 281
    //   418: astore 10
    //   420: aload 10
    //   422: invokevirtual 193	java/io/IOException:printStackTrace	()V
    //   425: goto -46 -> 379
    //   428: astore 17
    //   430: aconst_null
    //   431: astore 18
    //   433: aconst_null
    //   434: astore 19
    //   436: aload_0
    //   437: getfield 19	com/gensee/net/AbsRtAction$2:val$response	Lcom/gensee/net/AbsRtAction$Response;
    //   440: bipush 153
    //   442: ldc 53
    //   444: invokeinterface 59 3 0
    //   449: aload 18
    //   451: ifnull +8 -> 459
    //   454: aload 18
    //   456: invokevirtual 179	java/net/HttpURLConnection:disconnect	()V
    //   459: aload_1
    //   460: ifnull +7 -> 467
    //   463: aload_1
    //   464: invokevirtual 180	java/io/InputStreamReader:close	()V
    //   467: aload 19
    //   469: ifnull -441 -> 28
    //   472: aload_0
    //   473: getfield 19	com/gensee/net/AbsRtAction$2:val$response	Lcom/gensee/net/AbsRtAction$Response;
    //   476: aload 19
    //   478: invokeinterface 183 2 0
    //   483: return
    //   484: astore 21
    //   486: aload 21
    //   488: invokevirtual 193	java/io/IOException:printStackTrace	()V
    //   491: goto -24 -> 467
    //   494: astore 15
    //   496: aconst_null
    //   497: astore 8
    //   499: aconst_null
    //   500: astore 4
    //   502: aload_0
    //   503: getfield 19	com/gensee/net/AbsRtAction$2:val$response	Lcom/gensee/net/AbsRtAction$Response;
    //   506: bipush 155
    //   508: ldc 53
    //   510: invokeinterface 59 3 0
    //   515: aload 15
    //   517: invokestatic 190	com/gensee/utils/GenseeLog:e	(Ljava/lang/Exception;)V
    //   520: aload 8
    //   522: ifnull +8 -> 530
    //   525: aload 8
    //   527: invokevirtual 179	java/net/HttpURLConnection:disconnect	()V
    //   530: aload_1
    //   531: ifnull +7 -> 538
    //   534: aload_1
    //   535: invokevirtual 180	java/io/InputStreamReader:close	()V
    //   538: aload 4
    //   540: ifnull -512 -> 28
    //   543: aload_0
    //   544: getfield 19	com/gensee/net/AbsRtAction$2:val$response	Lcom/gensee/net/AbsRtAction$Response;
    //   547: aload 4
    //   549: invokeinterface 183 2 0
    //   554: return
    //   555: astore 16
    //   557: aload 16
    //   559: invokevirtual 193	java/io/IOException:printStackTrace	()V
    //   562: goto -24 -> 538
    //   565: astore 13
    //   567: aconst_null
    //   568: astore 8
    //   570: aconst_null
    //   571: astore 4
    //   573: aload_0
    //   574: getfield 19	com/gensee/net/AbsRtAction$2:val$response	Lcom/gensee/net/AbsRtAction$Response;
    //   577: bipush 147
    //   579: ldc 53
    //   581: invokeinterface 59 3 0
    //   586: aload 13
    //   588: invokestatic 190	com/gensee/utils/GenseeLog:e	(Ljava/lang/Exception;)V
    //   591: aload 8
    //   593: ifnull +8 -> 601
    //   596: aload 8
    //   598: invokevirtual 179	java/net/HttpURLConnection:disconnect	()V
    //   601: aload_1
    //   602: ifnull +7 -> 609
    //   605: aload_1
    //   606: invokevirtual 180	java/io/InputStreamReader:close	()V
    //   609: aload 4
    //   611: ifnull -583 -> 28
    //   614: aload_0
    //   615: getfield 19	com/gensee/net/AbsRtAction$2:val$response	Lcom/gensee/net/AbsRtAction$Response;
    //   618: aload 4
    //   620: invokeinterface 183 2 0
    //   625: return
    //   626: astore 14
    //   628: aload 14
    //   630: invokevirtual 193	java/io/IOException:printStackTrace	()V
    //   633: goto -24 -> 609
    //   636: astore 11
    //   638: aconst_null
    //   639: astore 8
    //   641: aconst_null
    //   642: astore 4
    //   644: aload_0
    //   645: getfield 19	com/gensee/net/AbsRtAction$2:val$response	Lcom/gensee/net/AbsRtAction$Response;
    //   648: bipush 154
    //   650: ldc 53
    //   652: invokeinterface 59 3 0
    //   657: aload 11
    //   659: invokestatic 190	com/gensee/utils/GenseeLog:e	(Ljava/lang/Exception;)V
    //   662: aload 8
    //   664: ifnull +8 -> 672
    //   667: aload 8
    //   669: invokevirtual 179	java/net/HttpURLConnection:disconnect	()V
    //   672: aload_1
    //   673: ifnull +7 -> 680
    //   676: aload_1
    //   677: invokevirtual 180	java/io/InputStreamReader:close	()V
    //   680: aload 4
    //   682: ifnull -654 -> 28
    //   685: aload_0
    //   686: getfield 19	com/gensee/net/AbsRtAction$2:val$response	Lcom/gensee/net/AbsRtAction$Response;
    //   689: aload 4
    //   691: invokeinterface 183 2 0
    //   696: return
    //   697: astore 12
    //   699: aload 12
    //   701: invokevirtual 193	java/io/IOException:printStackTrace	()V
    //   704: goto -24 -> 680
    //   707: astore 6
    //   709: aconst_null
    //   710: astore 8
    //   712: aconst_null
    //   713: astore 4
    //   715: aload 8
    //   717: ifnull +8 -> 725
    //   720: aload 8
    //   722: invokevirtual 179	java/net/HttpURLConnection:disconnect	()V
    //   725: aload_1
    //   726: ifnull +7 -> 733
    //   729: aload_1
    //   730: invokevirtual 180	java/io/InputStreamReader:close	()V
    //   733: aload 4
    //   735: ifnull +14 -> 749
    //   738: aload_0
    //   739: getfield 19	com/gensee/net/AbsRtAction$2:val$response	Lcom/gensee/net/AbsRtAction$Response;
    //   742: aload 4
    //   744: invokeinterface 183 2 0
    //   749: aload 6
    //   751: athrow
    //   752: astore 9
    //   754: aload 9
    //   756: invokevirtual 193	java/io/IOException:printStackTrace	()V
    //   759: goto -26 -> 733
    //   762: astore 55
    //   764: aload 55
    //   766: invokevirtual 193	java/io/IOException:printStackTrace	()V
    //   769: goto -468 -> 301
    //   772: astore 30
    //   774: aload 18
    //   776: astore 31
    //   778: aload 30
    //   780: astore 6
    //   782: aload 31
    //   784: astore 8
    //   786: aconst_null
    //   787: astore 4
    //   789: aconst_null
    //   790: astore_1
    //   791: goto -76 -> 715
    //   794: astore 40
    //   796: aload 18
    //   798: astore 8
    //   800: aload 40
    //   802: astore 6
    //   804: aload 33
    //   806: astore_1
    //   807: aconst_null
    //   808: astore 4
    //   810: goto -95 -> 715
    //   813: astore 53
    //   815: aload 18
    //   817: astore 8
    //   819: aload 53
    //   821: astore 6
    //   823: aload 33
    //   825: astore 54
    //   827: aload 44
    //   829: astore 4
    //   831: aload 54
    //   833: astore_1
    //   834: goto -119 -> 715
    //   837: astore 6
    //   839: aload_3
    //   840: astore 7
    //   842: aload 5
    //   844: astore 8
    //   846: aload 7
    //   848: astore_1
    //   849: goto -134 -> 715
    //   852: astore 20
    //   854: aload 19
    //   856: astore 4
    //   858: aload 18
    //   860: astore 8
    //   862: aload 20
    //   864: astore 6
    //   866: goto -151 -> 715
    //   869: astore 6
    //   871: goto -156 -> 715
    //   874: astore 28
    //   876: aload 18
    //   878: astore 29
    //   880: aload 28
    //   882: astore 11
    //   884: aload 29
    //   886: astore 8
    //   888: aconst_null
    //   889: astore 4
    //   891: aconst_null
    //   892: astore_1
    //   893: goto -249 -> 644
    //   896: astore 39
    //   898: aload 18
    //   900: astore 8
    //   902: aload 39
    //   904: astore 11
    //   906: aload 33
    //   908: astore_1
    //   909: aconst_null
    //   910: astore 4
    //   912: goto -268 -> 644
    //   915: astore 51
    //   917: aload 18
    //   919: astore 8
    //   921: aload 51
    //   923: astore 11
    //   925: aload 33
    //   927: astore 52
    //   929: aload 44
    //   931: astore 4
    //   933: aload 52
    //   935: astore_1
    //   936: goto -292 -> 644
    //   939: astore 26
    //   941: aload 18
    //   943: astore 27
    //   945: aload 26
    //   947: astore 13
    //   949: aload 27
    //   951: astore 8
    //   953: aconst_null
    //   954: astore 4
    //   956: aconst_null
    //   957: astore_1
    //   958: goto -385 -> 573
    //   961: astore 38
    //   963: aload 18
    //   965: astore 8
    //   967: aload 38
    //   969: astore 13
    //   971: aload 33
    //   973: astore_1
    //   974: aconst_null
    //   975: astore 4
    //   977: goto -404 -> 573
    //   980: astore 49
    //   982: aload 18
    //   984: astore 8
    //   986: aload 49
    //   988: astore 13
    //   990: aload 33
    //   992: astore 50
    //   994: aload 44
    //   996: astore 4
    //   998: aload 50
    //   1000: astore_1
    //   1001: goto -428 -> 573
    //   1004: astore 24
    //   1006: aload 18
    //   1008: astore 25
    //   1010: aload 24
    //   1012: astore 15
    //   1014: aload 25
    //   1016: astore 8
    //   1018: aconst_null
    //   1019: astore 4
    //   1021: aconst_null
    //   1022: astore_1
    //   1023: goto -521 -> 502
    //   1026: astore 37
    //   1028: aload 18
    //   1030: astore 8
    //   1032: aload 37
    //   1034: astore 15
    //   1036: aload 33
    //   1038: astore_1
    //   1039: aconst_null
    //   1040: astore 4
    //   1042: goto -540 -> 502
    //   1045: astore 47
    //   1047: aload 18
    //   1049: astore 8
    //   1051: aload 47
    //   1053: astore 15
    //   1055: aload 33
    //   1057: astore 48
    //   1059: aload 44
    //   1061: astore 4
    //   1063: aload 48
    //   1065: astore_1
    //   1066: goto -564 -> 502
    //   1069: astore 23
    //   1071: aconst_null
    //   1072: astore 19
    //   1074: aconst_null
    //   1075: astore_1
    //   1076: goto -640 -> 436
    //   1079: astore 36
    //   1081: aload 33
    //   1083: astore_1
    //   1084: aconst_null
    //   1085: astore 19
    //   1087: goto -651 -> 436
    //   1090: astore 46
    //   1092: aload 44
    //   1094: astore 19
    //   1096: aload 33
    //   1098: astore_1
    //   1099: goto -663 -> 436
    //   1102: astore_2
    //   1103: aconst_null
    //   1104: astore_3
    //   1105: aconst_null
    //   1106: astore 4
    //   1108: aconst_null
    //   1109: astore 5
    //   1111: goto -767 -> 344
    //   1114: astore 22
    //   1116: aload 18
    //   1118: astore 5
    //   1120: aload 22
    //   1122: astore_2
    //   1123: aconst_null
    //   1124: astore_3
    //   1125: aconst_null
    //   1126: astore 4
    //   1128: goto -784 -> 344
    //   1131: astore 45
    //   1133: aload 33
    //   1135: astore_3
    //   1136: aload 44
    //   1138: astore 4
    //   1140: aload 18
    //   1142: astore 5
    //   1144: aload 45
    //   1146: astore_2
    //   1147: goto -803 -> 344
    //
    // Exception table:
    //   from	to	target	type
    //   192	212	329	java/net/UnknownHostException
    //   212	219	329	java/net/UnknownHostException
    //   224	231	329	java/net/UnknownHostException
    //   318	326	329	java/net/UnknownHostException
    //   375	379	418	java/io/IOException
    //   29	84	428	java/io/FileNotFoundException
    //   463	467	484	java/io/IOException
    //   29	84	494	java/net/SocketTimeoutException
    //   534	538	555	java/io/IOException
    //   29	84	565	java/net/ConnectException
    //   605	609	626	java/io/IOException
    //   29	84	636	java/lang/Exception
    //   676	680	697	java/io/IOException
    //   29	84	707	finally
    //   729	733	752	java/io/IOException
    //   296	301	762	java/io/IOException
    //   84	192	772	finally
    //   396	409	772	finally
    //   192	212	794	finally
    //   212	219	794	finally
    //   224	231	794	finally
    //   318	326	794	finally
    //   235	281	813	finally
    //   344	361	837	finally
    //   436	449	852	finally
    //   502	520	869	finally
    //   573	591	869	finally
    //   644	662	869	finally
    //   84	192	874	java/lang/Exception
    //   396	409	874	java/lang/Exception
    //   192	212	896	java/lang/Exception
    //   212	219	896	java/lang/Exception
    //   224	231	896	java/lang/Exception
    //   318	326	896	java/lang/Exception
    //   235	281	915	java/lang/Exception
    //   84	192	939	java/net/ConnectException
    //   396	409	939	java/net/ConnectException
    //   192	212	961	java/net/ConnectException
    //   212	219	961	java/net/ConnectException
    //   224	231	961	java/net/ConnectException
    //   318	326	961	java/net/ConnectException
    //   235	281	980	java/net/ConnectException
    //   84	192	1004	java/net/SocketTimeoutException
    //   396	409	1004	java/net/SocketTimeoutException
    //   192	212	1026	java/net/SocketTimeoutException
    //   212	219	1026	java/net/SocketTimeoutException
    //   224	231	1026	java/net/SocketTimeoutException
    //   318	326	1026	java/net/SocketTimeoutException
    //   235	281	1045	java/net/SocketTimeoutException
    //   84	192	1069	java/io/FileNotFoundException
    //   396	409	1069	java/io/FileNotFoundException
    //   192	212	1079	java/io/FileNotFoundException
    //   212	219	1079	java/io/FileNotFoundException
    //   224	231	1079	java/io/FileNotFoundException
    //   318	326	1079	java/io/FileNotFoundException
    //   235	281	1090	java/io/FileNotFoundException
    //   29	84	1102	java/net/UnknownHostException
    //   84	192	1114	java/net/UnknownHostException
    //   396	409	1114	java/net/UnknownHostException
    //   235	281	1131	java/net/UnknownHostException
  }
}

/* Location:           C:\Androidnixiangzhushou\zikao_classes_dex2jar.jar
 * Qualified Name:     com.gensee.net.AbsRtAction.2
 * JD-Core Version:    0.6.0
 */