package com.alipay.android.phone.mrpc.core;

import android.content.Context;
import android.text.TextUtils;
import android.webkit.CookieManager;
import java.io.IOException;
import java.io.InputStream;
import java.io.OutputStream;
import java.net.URI;
import java.net.URL;
import java.util.HashMap;
import java.util.concurrent.Callable;
import org.apache.http.Header;
import org.apache.http.HttpEntity;
import org.apache.http.HttpHost;
import org.apache.http.HttpResponse;
import org.apache.http.client.CookieStore;
import org.apache.http.client.HttpRequestRetryHandler;
import org.apache.http.client.methods.HttpGet;
import org.apache.http.client.methods.HttpPost;
import org.apache.http.client.methods.HttpUriRequest;
import org.apache.http.entity.AbstractHttpEntity;
import org.apache.http.entity.ByteArrayEntity;
import org.apache.http.impl.client.BasicCookieStore;
import org.apache.http.protocol.BasicHttpContext;
import org.apache.http.protocol.HttpContext;

public final class q
  implements Callable<u>
{
  private static final HttpRequestRetryHandler e = new ad();
  protected l a;
  protected Context b;
  protected o c;
  String d;
  private HttpUriRequest f;
  private HttpContext g = new BasicHttpContext();
  private CookieStore h = new BasicCookieStore();
  private CookieManager i;
  private AbstractHttpEntity j;
  private HttpHost k;
  private URL l;
  private int m = 0;
  private boolean n = false;
  private boolean o = false;
  private String p = null;
  private String q;

  public q(l paraml, o paramo)
  {
    this.a = paraml;
    this.b = this.a.a;
    this.c = paramo;
  }

  private static long a(String[] paramArrayOfString)
  {
    for (int i1 = 0; i1 < paramArrayOfString.length; i1++)
    {
      if ((!"max-age".equalsIgnoreCase(paramArrayOfString[i1])) || (paramArrayOfString[(i1 + 1)] == null))
        continue;
      int i2 = i1 + 1;
      try
      {
        long l1 = Long.parseLong(paramArrayOfString[i2]);
        return l1;
      }
      catch (Exception localException)
      {
      }
    }
    return 0L;
  }

  private static HttpUrlHeader a(HttpResponse paramHttpResponse)
  {
    HttpUrlHeader localHttpUrlHeader = new HttpUrlHeader();
    for (Header localHeader : paramHttpResponse.getAllHeaders())
      localHttpUrlHeader.setHead(localHeader.getName(), localHeader.getValue());
    return localHttpUrlHeader;
  }

  // ERROR //
  private u a(HttpResponse paramHttpResponse, int paramInt, String paramString)
  {
    // Byte code:
    //   0: new 122	java/lang/StringBuilder
    //   3: dup
    //   4: ldc 124
    //   6: invokespecial 127	java/lang/StringBuilder:<init>	(Ljava/lang/String;)V
    //   9: invokestatic 133	java/lang/Thread:currentThread	()Ljava/lang/Thread;
    //   12: invokevirtual 137	java/lang/Thread:getId	()J
    //   15: invokevirtual 141	java/lang/StringBuilder:append	(J)Ljava/lang/StringBuilder;
    //   18: pop
    //   19: aload_1
    //   20: invokeinterface 145 1 0
    //   25: astore 5
    //   27: aload 5
    //   29: ifnull +287 -> 316
    //   32: aload_1
    //   33: invokeinterface 149 1 0
    //   38: invokeinterface 155 1 0
    //   43: sipush 200
    //   46: if_icmpne +270 -> 316
    //   49: new 122	java/lang/StringBuilder
    //   52: dup
    //   53: ldc 157
    //   55: invokespecial 127	java/lang/StringBuilder:<init>	(Ljava/lang/String;)V
    //   58: invokestatic 133	java/lang/Thread:currentThread	()Ljava/lang/Thread;
    //   61: invokevirtual 137	java/lang/Thread:getId	()J
    //   64: invokevirtual 141	java/lang/StringBuilder:append	(J)Ljava/lang/StringBuilder;
    //   67: pop
    //   68: new 159	java/io/ByteArrayOutputStream
    //   71: dup
    //   72: invokespecial 160	java/io/ByteArrayOutputStream:<init>	()V
    //   75: astore 9
    //   77: invokestatic 165	java/lang/System:currentTimeMillis	()J
    //   80: lstore 13
    //   82: aload_0
    //   83: aload 5
    //   85: aload 9
    //   87: invokespecial 168	com/alipay/android/phone/mrpc/core/q:a	(Lorg/apache/http/HttpEntity;Ljava/io/OutputStream;)V
    //   90: aload 9
    //   92: invokevirtual 172	java/io/ByteArrayOutputStream:toByteArray	()[B
    //   95: astore 15
    //   97: aload_0
    //   98: iconst_0
    //   99: putfield 65	com/alipay/android/phone/mrpc/core/q:o	Z
    //   102: aload_0
    //   103: getfield 69	com/alipay/android/phone/mrpc/core/q:a	Lcom/alipay/android/phone/mrpc/core/l;
    //   106: invokestatic 165	java/lang/System:currentTimeMillis	()J
    //   109: lload 13
    //   111: lsub
    //   112: invokevirtual 175	com/alipay/android/phone/mrpc/core/l:c	(J)V
    //   115: aload_0
    //   116: getfield 69	com/alipay/android/phone/mrpc/core/q:a	Lcom/alipay/android/phone/mrpc/core/l;
    //   119: aload 15
    //   121: arraylength
    //   122: i2l
    //   123: invokevirtual 177	com/alipay/android/phone/mrpc/core/l:a	(J)V
    //   126: new 122	java/lang/StringBuilder
    //   129: dup
    //   130: ldc 179
    //   132: invokespecial 127	java/lang/StringBuilder:<init>	(Ljava/lang/String;)V
    //   135: aload 15
    //   137: arraylength
    //   138: invokevirtual 182	java/lang/StringBuilder:append	(I)Ljava/lang/StringBuilder;
    //   141: pop
    //   142: new 184	com/alipay/android/phone/mrpc/core/p
    //   145: dup
    //   146: aload_1
    //   147: invokestatic 186	com/alipay/android/phone/mrpc/core/q:a	(Lorg/apache/http/HttpResponse;)Lcom/alipay/android/phone/mrpc/core/HttpUrlHeader;
    //   150: iload_2
    //   151: aload_3
    //   152: aload 15
    //   154: invokespecial 189	com/alipay/android/phone/mrpc/core/p:<init>	(Lcom/alipay/android/phone/mrpc/core/HttpUrlHeader;ILjava/lang/String;[B)V
    //   157: astore 17
    //   159: aload_1
    //   160: invokestatic 192	com/alipay/android/phone/mrpc/core/q:b	(Lorg/apache/http/HttpResponse;)J
    //   163: lstore 18
    //   165: aload_1
    //   166: invokeinterface 145 1 0
    //   171: invokeinterface 198 1 0
    //   176: astore 20
    //   178: aload 20
    //   180: ifnull +167 -> 347
    //   183: aload 20
    //   185: invokeinterface 113 1 0
    //   190: invokestatic 201	com/alipay/android/phone/mrpc/core/q:a	(Ljava/lang/String;)Ljava/util/HashMap;
    //   193: astore 21
    //   195: aload 21
    //   197: ldc 203
    //   199: invokevirtual 209	java/util/HashMap:get	(Ljava/lang/Object;)Ljava/lang/Object;
    //   202: checkcast 84	java/lang/String
    //   205: astore 22
    //   207: aload 21
    //   209: ldc 211
    //   211: invokevirtual 209	java/util/HashMap:get	(Ljava/lang/Object;)Ljava/lang/Object;
    //   214: checkcast 84	java/lang/String
    //   217: astore 23
    //   219: aload 17
    //   221: aload 23
    //   223: invokevirtual 213	com/alipay/android/phone/mrpc/core/p:b	(Ljava/lang/String;)V
    //   226: aload 17
    //   228: aload 22
    //   230: invokevirtual 215	com/alipay/android/phone/mrpc/core/p:a	(Ljava/lang/String;)V
    //   233: aload 17
    //   235: invokestatic 165	java/lang/System:currentTimeMillis	()J
    //   238: invokevirtual 216	com/alipay/android/phone/mrpc/core/p:a	(J)V
    //   241: aload 17
    //   243: lload 18
    //   245: invokevirtual 218	com/alipay/android/phone/mrpc/core/p:b	(J)V
    //   248: aload 9
    //   250: invokevirtual 221	java/io/ByteArrayOutputStream:close	()V
    //   253: aload 17
    //   255: astore 6
    //   257: aload 6
    //   259: areturn
    //   260: astore 24
    //   262: new 223	java/lang/RuntimeException
    //   265: dup
    //   266: ldc 225
    //   268: aload 24
    //   270: invokevirtual 229	java/io/IOException:getCause	()Ljava/lang/Throwable;
    //   273: invokespecial 232	java/lang/RuntimeException:<init>	(Ljava/lang/String;Ljava/lang/Throwable;)V
    //   276: athrow
    //   277: astore 25
    //   279: aconst_null
    //   280: astore 11
    //   282: aload 25
    //   284: astore 10
    //   286: aload 11
    //   288: ifnull +8 -> 296
    //   291: aload 11
    //   293: invokevirtual 221	java/io/ByteArrayOutputStream:close	()V
    //   296: aload 10
    //   298: athrow
    //   299: astore 12
    //   301: new 223	java/lang/RuntimeException
    //   304: dup
    //   305: ldc 225
    //   307: aload 12
    //   309: invokevirtual 229	java/io/IOException:getCause	()Ljava/lang/Throwable;
    //   312: invokespecial 232	java/lang/RuntimeException:<init>	(Ljava/lang/String;Ljava/lang/Throwable;)V
    //   315: athrow
    //   316: aconst_null
    //   317: astore 6
    //   319: aload 5
    //   321: ifnonnull -64 -> 257
    //   324: aload_1
    //   325: invokeinterface 149 1 0
    //   330: invokeinterface 155 1 0
    //   335: pop
    //   336: aconst_null
    //   337: areturn
    //   338: astore 10
    //   340: aload 9
    //   342: astore 11
    //   344: goto -58 -> 286
    //   347: aconst_null
    //   348: astore 22
    //   350: aconst_null
    //   351: astore 23
    //   353: goto -134 -> 219
    //
    // Exception table:
    //   from	to	target	type
    //   248	253	260	java/io/IOException
    //   68	77	277	finally
    //   291	296	299	java/io/IOException
    //   77	178	338	finally
    //   183	219	338	finally
    //   219	248	338	finally
  }

  private static HashMap<String, String> a(String paramString)
  {
    HashMap localHashMap = new HashMap();
    String[] arrayOfString1 = paramString.split(";");
    int i1 = arrayOfString1.length;
    int i2 = 0;
    if (i2 < i1)
    {
      String str = arrayOfString1[i2];
      String[] arrayOfString2;
      if (str.indexOf('=') == -1)
      {
        arrayOfString2 = new String[2];
        arrayOfString2[0] = "Content-Type";
        arrayOfString2[1] = str;
      }
      while (true)
      {
        localHashMap.put(arrayOfString2[0], arrayOfString2[1]);
        i2++;
        break;
        arrayOfString2 = str.split("=");
      }
    }
    return localHashMap;
  }

  private void a(HttpEntity paramHttpEntity, OutputStream paramOutputStream)
  {
    InputStream localInputStream = b.a(paramHttpEntity);
    long l1 = paramHttpEntity.getContentLength();
    try
    {
      byte[] arrayOfByte = new byte[2048];
      while (true)
      {
        int i1 = localInputStream.read(arrayOfByte);
        if ((i1 == -1) || (this.c.h()))
          break;
        paramOutputStream.write(arrayOfByte, 0, i1);
        if ((this.c.f() == null) || (l1 <= 0L))
          continue;
        this.c.f();
      }
      paramOutputStream.flush();
      return;
    }
    catch (Exception localException)
    {
      localException.getCause();
      throw new IOException("HttpWorker Request Error!" + localException.getLocalizedMessage());
    }
    finally
    {
      r.a(localInputStream);
    }
    throw localObject;
  }

  private static long b(HttpResponse paramHttpResponse)
  {
    long l1 = 0L;
    Header localHeader1 = paramHttpResponse.getFirstHeader("Cache-Control");
    String[] arrayOfString;
    if (localHeader1 != null)
    {
      arrayOfString = localHeader1.getValue().split("=");
      if (arrayOfString.length < 2);
    }
    Header localHeader2;
    do
    {
      try
      {
        long l2 = a(arrayOfString);
        l1 = l2;
        return l1;
      }
      catch (NumberFormatException localNumberFormatException)
      {
      }
      localHeader2 = paramHttpResponse.getFirstHeader("Expires");
    }
    while (localHeader2 == null);
    return b.b(localHeader2.getValue()) - System.currentTimeMillis();
  }

  private URI b()
  {
    String str = this.c.a();
    if (this.d != null)
      str = this.d;
    if (str == null)
      throw new RuntimeException("url should not be null");
    return new URI(str);
  }

  private HttpUriRequest c()
  {
    if (this.f != null)
      return this.f;
    byte[] arrayOfByte;
    if (this.j == null)
    {
      arrayOfByte = this.c.b();
      String str = this.c.b("gzip");
      if (arrayOfByte != null)
      {
        if (!TextUtils.equals(str, "true"))
          break label112;
        this.j = b.a(arrayOfByte);
        this.j.setContentType(this.c.c());
      }
    }
    AbstractHttpEntity localAbstractHttpEntity = this.j;
    HttpPost localHttpPost;
    if (localAbstractHttpEntity != null)
    {
      localHttpPost = new HttpPost(b());
      localHttpPost.setEntity(localAbstractHttpEntity);
    }
    for (this.f = localHttpPost; ; this.f = new HttpGet(b()))
    {
      return this.f;
      label112: this.j = new ByteArrayEntity(arrayOfByte);
      break;
    }
  }

  // ERROR //
  private u d()
  {
    // Byte code:
    //   0: aload_0
    //   1: getfield 75	com/alipay/android/phone/mrpc/core/q:b	Landroid/content/Context;
    //   4: ldc_w 399
    //   7: invokevirtual 405	android/content/Context:getSystemService	(Ljava/lang/String;)Ljava/lang/Object;
    //   10: checkcast 407	android/net/ConnectivityManager
    //   13: invokevirtual 411	android/net/ConnectivityManager:getAllNetworkInfo	()[Landroid/net/NetworkInfo;
    //   16: astore 63
    //   18: aload 63
    //   20: ifnonnull +83 -> 103
    //   23: iconst_0
    //   24: istore 67
    //   26: iload 67
    //   28: ifne +124 -> 152
    //   31: new 375	com/alipay/android/phone/mrpc/core/HttpException
    //   34: dup
    //   35: iconst_1
    //   36: invokestatic 417	java/lang/Integer:valueOf	(I)Ljava/lang/Integer;
    //   39: ldc_w 419
    //   42: invokespecial 422	com/alipay/android/phone/mrpc/core/HttpException:<init>	(Ljava/lang/Integer;Ljava/lang/String;)V
    //   45: athrow
    //   46: astore 57
    //   48: aload_0
    //   49: invokespecial 424	com/alipay/android/phone/mrpc/core/q:e	()V
    //   52: aload_0
    //   53: getfield 77	com/alipay/android/phone/mrpc/core/q:c	Lcom/alipay/android/phone/mrpc/core/o;
    //   56: invokevirtual 277	com/alipay/android/phone/mrpc/core/o:f	()Lcom/alipay/android/phone/mrpc/core/ac;
    //   59: ifnull +28 -> 87
    //   62: aload_0
    //   63: getfield 77	com/alipay/android/phone/mrpc/core/q:c	Lcom/alipay/android/phone/mrpc/core/o;
    //   66: invokevirtual 277	com/alipay/android/phone/mrpc/core/o:f	()Lcom/alipay/android/phone/mrpc/core/ac;
    //   69: pop
    //   70: aload_0
    //   71: getfield 77	com/alipay/android/phone/mrpc/core/q:c	Lcom/alipay/android/phone/mrpc/core/o;
    //   74: pop
    //   75: aload 57
    //   77: invokevirtual 427	com/alipay/android/phone/mrpc/core/HttpException:getCode	()I
    //   80: pop
    //   81: aload 57
    //   83: invokevirtual 430	com/alipay/android/phone/mrpc/core/HttpException:getMsg	()Ljava/lang/String;
    //   86: pop
    //   87: new 122	java/lang/StringBuilder
    //   90: dup
    //   91: invokespecial 431	java/lang/StringBuilder:<init>	()V
    //   94: aload 57
    //   96: invokevirtual 434	java/lang/StringBuilder:append	(Ljava/lang/Object;)Ljava/lang/StringBuilder;
    //   99: pop
    //   100: aload 57
    //   102: athrow
    //   103: aload 63
    //   105: arraylength
    //   106: istore 64
    //   108: iconst_0
    //   109: istore 65
    //   111: iload 65
    //   113: iload 64
    //   115: if_icmpge +1734 -> 1849
    //   118: aload 63
    //   120: iload 65
    //   122: aaload
    //   123: astore 66
    //   125: aload 66
    //   127: ifnull +1728 -> 1855
    //   130: aload 66
    //   132: invokevirtual 439	android/net/NetworkInfo:isAvailable	()Z
    //   135: ifeq +1720 -> 1855
    //   138: aload 66
    //   140: invokevirtual 442	android/net/NetworkInfo:isConnectedOrConnecting	()Z
    //   143: ifeq +1712 -> 1855
    //   146: iconst_1
    //   147: istore 67
    //   149: goto -123 -> 26
    //   152: aload_0
    //   153: getfield 77	com/alipay/android/phone/mrpc/core/q:c	Lcom/alipay/android/phone/mrpc/core/o;
    //   156: invokevirtual 277	com/alipay/android/phone/mrpc/core/o:f	()Lcom/alipay/android/phone/mrpc/core/ac;
    //   159: ifnull +16 -> 175
    //   162: aload_0
    //   163: getfield 77	com/alipay/android/phone/mrpc/core/q:c	Lcom/alipay/android/phone/mrpc/core/o;
    //   166: invokevirtual 277	com/alipay/android/phone/mrpc/core/o:f	()Lcom/alipay/android/phone/mrpc/core/ac;
    //   169: pop
    //   170: aload_0
    //   171: getfield 77	com/alipay/android/phone/mrpc/core/q:c	Lcom/alipay/android/phone/mrpc/core/o;
    //   174: pop
    //   175: aload_0
    //   176: getfield 77	com/alipay/android/phone/mrpc/core/q:c	Lcom/alipay/android/phone/mrpc/core/o;
    //   179: invokevirtual 445	com/alipay/android/phone/mrpc/core/o:d	()Ljava/util/ArrayList;
    //   182: astore 68
    //   184: aload 68
    //   186: ifnull +72 -> 258
    //   189: aload 68
    //   191: invokevirtual 450	java/util/ArrayList:isEmpty	()Z
    //   194: ifne +64 -> 258
    //   197: aload 68
    //   199: invokevirtual 454	java/util/ArrayList:iterator	()Ljava/util/Iterator;
    //   202: astore 102
    //   204: aload 102
    //   206: invokeinterface 459 1 0
    //   211: ifeq +47 -> 258
    //   214: aload 102
    //   216: invokeinterface 463 1 0
    //   221: checkcast 106	org/apache/http/Header
    //   224: astore 103
    //   226: aload_0
    //   227: invokespecial 465	com/alipay/android/phone/mrpc/core/q:c	()Lorg/apache/http/client/methods/HttpUriRequest;
    //   230: aload 103
    //   232: invokeinterface 471 2 0
    //   237: goto -33 -> 204
    //   240: astore 56
    //   242: new 223	java/lang/RuntimeException
    //   245: dup
    //   246: ldc_w 473
    //   249: aload 56
    //   251: invokevirtual 474	java/net/URISyntaxException:getCause	()Ljava/lang/Throwable;
    //   254: invokespecial 232	java/lang/RuntimeException:<init>	(Ljava/lang/String;Ljava/lang/Throwable;)V
    //   257: athrow
    //   258: aload_0
    //   259: invokespecial 465	com/alipay/android/phone/mrpc/core/q:c	()Lorg/apache/http/client/methods/HttpUriRequest;
    //   262: invokestatic 477	com/alipay/android/phone/mrpc/core/b:a	(Lorg/apache/http/HttpRequest;)V
    //   265: aload_0
    //   266: invokespecial 465	com/alipay/android/phone/mrpc/core/q:c	()Lorg/apache/http/client/methods/HttpUriRequest;
    //   269: invokestatic 479	com/alipay/android/phone/mrpc/core/b:b	(Lorg/apache/http/HttpRequest;)V
    //   272: aload_0
    //   273: invokespecial 465	com/alipay/android/phone/mrpc/core/q:c	()Lorg/apache/http/client/methods/HttpUriRequest;
    //   276: ldc_w 481
    //   279: aload_0
    //   280: invokespecial 484	com/alipay/android/phone/mrpc/core/q:i	()Landroid/webkit/CookieManager;
    //   283: aload_0
    //   284: getfield 77	com/alipay/android/phone/mrpc/core/q:c	Lcom/alipay/android/phone/mrpc/core/o;
    //   287: invokevirtual 315	com/alipay/android/phone/mrpc/core/o:a	()Ljava/lang/String;
    //   290: invokevirtual 489	android/webkit/CookieManager:getCookie	(Ljava/lang/String;)Ljava/lang/String;
    //   293: invokeinterface 491 3 0
    //   298: aload_0
    //   299: getfield 54	com/alipay/android/phone/mrpc/core/q:g	Lorg/apache/http/protocol/HttpContext;
    //   302: ldc_w 493
    //   305: aload_0
    //   306: getfield 59	com/alipay/android/phone/mrpc/core/q:h	Lorg/apache/http/client/CookieStore;
    //   309: invokeinterface 499 3 0
    //   314: aload_0
    //   315: getfield 69	com/alipay/android/phone/mrpc/core/q:a	Lcom/alipay/android/phone/mrpc/core/l;
    //   318: invokevirtual 502	com/alipay/android/phone/mrpc/core/l:a	()Lcom/alipay/android/phone/mrpc/core/b;
    //   321: getstatic 47	com/alipay/android/phone/mrpc/core/q:e	Lorg/apache/http/client/HttpRequestRetryHandler;
    //   324: invokevirtual 505	com/alipay/android/phone/mrpc/core/b:a	(Lorg/apache/http/client/HttpRequestRetryHandler;)V
    //   327: invokestatic 165	java/lang/System:currentTimeMillis	()J
    //   330: lstore 69
    //   332: new 122	java/lang/StringBuilder
    //   335: dup
    //   336: ldc_w 507
    //   339: invokespecial 127	java/lang/StringBuilder:<init>	(Ljava/lang/String;)V
    //   342: aload_0
    //   343: invokespecial 509	com/alipay/android/phone/mrpc/core/q:f	()Ljava/lang/String;
    //   346: invokevirtual 294	java/lang/StringBuilder:append	(Ljava/lang/String;)Ljava/lang/StringBuilder;
    //   349: ldc_w 511
    //   352: invokevirtual 294	java/lang/StringBuilder:append	(Ljava/lang/String;)Ljava/lang/StringBuilder;
    //   355: aload_0
    //   356: getfield 326	com/alipay/android/phone/mrpc/core/q:f	Lorg/apache/http/client/methods/HttpUriRequest;
    //   359: invokeinterface 514 1 0
    //   364: invokevirtual 515	java/net/URI:toString	()Ljava/lang/String;
    //   367: invokevirtual 294	java/lang/StringBuilder:append	(Ljava/lang/String;)Ljava/lang/StringBuilder;
    //   370: pop
    //   371: aload_0
    //   372: getfield 69	com/alipay/android/phone/mrpc/core/q:a	Lcom/alipay/android/phone/mrpc/core/l;
    //   375: invokevirtual 502	com/alipay/android/phone/mrpc/core/l:a	()Lcom/alipay/android/phone/mrpc/core/b;
    //   378: invokevirtual 519	com/alipay/android/phone/mrpc/core/b:getParams	()Lorg/apache/http/params/HttpParams;
    //   381: astore 72
    //   383: aload_0
    //   384: getfield 75	com/alipay/android/phone/mrpc/core/q:b	Landroid/content/Context;
    //   387: ldc_w 399
    //   390: invokevirtual 405	android/content/Context:getSystemService	(Ljava/lang/String;)Ljava/lang/Object;
    //   393: checkcast 407	android/net/ConnectivityManager
    //   396: invokevirtual 523	android/net/ConnectivityManager:getActiveNetworkInfo	()Landroid/net/NetworkInfo;
    //   399: astore 73
    //   401: aload 73
    //   403: ifnull +1440 -> 1843
    //   406: aload 73
    //   408: invokevirtual 439	android/net/NetworkInfo:isAvailable	()Z
    //   411: ifeq +1432 -> 1843
    //   414: invokestatic 528	android/net/Proxy:getDefaultHost	()Ljava/lang/String;
    //   417: astore 100
    //   419: invokestatic 531	android/net/Proxy:getDefaultPort	()I
    //   422: istore 101
    //   424: aload 100
    //   426: ifnull +1417 -> 1843
    //   429: new 533	org/apache/http/HttpHost
    //   432: dup
    //   433: aload 100
    //   435: iload 101
    //   437: invokespecial 536	org/apache/http/HttpHost:<init>	(Ljava/lang/String;I)V
    //   440: astore 74
    //   442: aload 74
    //   444: ifnull +31 -> 475
    //   447: aload 74
    //   449: invokevirtual 539	org/apache/http/HttpHost:getHostName	()Ljava/lang/String;
    //   452: ldc_w 541
    //   455: invokestatic 343	android/text/TextUtils:equals	(Ljava/lang/CharSequence;Ljava/lang/CharSequence;)Z
    //   458: ifeq +17 -> 475
    //   461: aload 74
    //   463: invokevirtual 544	org/apache/http/HttpHost:getPort	()I
    //   466: sipush 8087
    //   469: if_icmpne +6 -> 475
    //   472: aconst_null
    //   473: astore 74
    //   475: aload 72
    //   477: ldc_w 546
    //   480: aload 74
    //   482: invokeinterface 552 3 0
    //   487: pop
    //   488: aload_0
    //   489: getfield 554	com/alipay/android/phone/mrpc/core/q:k	Lorg/apache/http/HttpHost;
    //   492: ifnull +326 -> 818
    //   495: aload_0
    //   496: getfield 554	com/alipay/android/phone/mrpc/core/q:k	Lorg/apache/http/HttpHost;
    //   499: astore 77
    //   501: aload_0
    //   502: invokespecial 556	com/alipay/android/phone/mrpc/core/q:g	()I
    //   505: bipush 80
    //   507: if_icmpne +19 -> 526
    //   510: new 533	org/apache/http/HttpHost
    //   513: dup
    //   514: aload_0
    //   515: invokespecial 559	com/alipay/android/phone/mrpc/core/q:h	()Ljava/net/URL;
    //   518: invokevirtual 564	java/net/URL:getHost	()Ljava/lang/String;
    //   521: invokespecial 565	org/apache/http/HttpHost:<init>	(Ljava/lang/String;)V
    //   524: astore 77
    //   526: aload_0
    //   527: getfield 69	com/alipay/android/phone/mrpc/core/q:a	Lcom/alipay/android/phone/mrpc/core/l;
    //   530: invokevirtual 502	com/alipay/android/phone/mrpc/core/l:a	()Lcom/alipay/android/phone/mrpc/core/b;
    //   533: aload 77
    //   535: aload_0
    //   536: getfield 326	com/alipay/android/phone/mrpc/core/q:f	Lorg/apache/http/client/methods/HttpUriRequest;
    //   539: aload_0
    //   540: getfield 54	com/alipay/android/phone/mrpc/core/q:g	Lorg/apache/http/protocol/HttpContext;
    //   543: invokevirtual 569	com/alipay/android/phone/mrpc/core/b:execute	(Lorg/apache/http/HttpHost;Lorg/apache/http/HttpRequest;Lorg/apache/http/protocol/HttpContext;)Lorg/apache/http/HttpResponse;
    //   546: astore 78
    //   548: invokestatic 165	java/lang/System:currentTimeMillis	()J
    //   551: lstore 79
    //   553: aload_0
    //   554: getfield 69	com/alipay/android/phone/mrpc/core/q:a	Lcom/alipay/android/phone/mrpc/core/l;
    //   557: lload 79
    //   559: lload 69
    //   561: lsub
    //   562: invokevirtual 570	com/alipay/android/phone/mrpc/core/l:b	(J)V
    //   565: aload_0
    //   566: getfield 59	com/alipay/android/phone/mrpc/core/q:h	Lorg/apache/http/client/CookieStore;
    //   569: invokeinterface 576 1 0
    //   574: astore 81
    //   576: aload_0
    //   577: getfield 77	com/alipay/android/phone/mrpc/core/q:c	Lcom/alipay/android/phone/mrpc/core/o;
    //   580: invokevirtual 578	com/alipay/android/phone/mrpc/core/o:e	()Z
    //   583: ifeq +10 -> 593
    //   586: aload_0
    //   587: invokespecial 484	com/alipay/android/phone/mrpc/core/q:i	()Landroid/webkit/CookieManager;
    //   590: invokevirtual 581	android/webkit/CookieManager:removeAllCookie	()V
    //   593: aload 81
    //   595: invokeinterface 584 1 0
    //   600: ifne +258 -> 858
    //   603: aload 81
    //   605: invokeinterface 585 1 0
    //   610: astore 95
    //   612: aload 95
    //   614: invokeinterface 459 1 0
    //   619: ifeq +239 -> 858
    //   622: aload 95
    //   624: invokeinterface 463 1 0
    //   629: checkcast 587	org/apache/http/cookie/Cookie
    //   632: astore 96
    //   634: aload 96
    //   636: invokeinterface 590 1 0
    //   641: ifnull -29 -> 612
    //   644: new 122	java/lang/StringBuilder
    //   647: dup
    //   648: invokespecial 431	java/lang/StringBuilder:<init>	()V
    //   651: aload 96
    //   653: invokeinterface 591 1 0
    //   658: invokevirtual 294	java/lang/StringBuilder:append	(Ljava/lang/String;)Ljava/lang/StringBuilder;
    //   661: ldc 249
    //   663: invokevirtual 294	java/lang/StringBuilder:append	(Ljava/lang/String;)Ljava/lang/StringBuilder;
    //   666: aload 96
    //   668: invokeinterface 592 1 0
    //   673: invokevirtual 294	java/lang/StringBuilder:append	(Ljava/lang/String;)Ljava/lang/StringBuilder;
    //   676: ldc_w 594
    //   679: invokevirtual 294	java/lang/StringBuilder:append	(Ljava/lang/String;)Ljava/lang/StringBuilder;
    //   682: aload 96
    //   684: invokeinterface 590 1 0
    //   689: invokevirtual 294	java/lang/StringBuilder:append	(Ljava/lang/String;)Ljava/lang/StringBuilder;
    //   692: astore 97
    //   694: aload 96
    //   696: invokeinterface 597 1 0
    //   701: ifeq +1160 -> 1861
    //   704: ldc_w 599
    //   707: astore 98
    //   709: aload 97
    //   711: aload 98
    //   713: invokevirtual 294	java/lang/StringBuilder:append	(Ljava/lang/String;)Ljava/lang/StringBuilder;
    //   716: invokevirtual 297	java/lang/StringBuilder:toString	()Ljava/lang/String;
    //   719: astore 99
    //   721: aload_0
    //   722: invokespecial 484	com/alipay/android/phone/mrpc/core/q:i	()Landroid/webkit/CookieManager;
    //   725: aload_0
    //   726: getfield 77	com/alipay/android/phone/mrpc/core/q:c	Lcom/alipay/android/phone/mrpc/core/o;
    //   729: invokevirtual 315	com/alipay/android/phone/mrpc/core/o:a	()Ljava/lang/String;
    //   732: aload 99
    //   734: invokevirtual 602	android/webkit/CookieManager:setCookie	(Ljava/lang/String;Ljava/lang/String;)V
    //   737: invokestatic 608	android/webkit/CookieSyncManager:getInstance	()Landroid/webkit/CookieSyncManager;
    //   740: invokevirtual 611	android/webkit/CookieSyncManager:sync	()V
    //   743: goto -131 -> 612
    //   746: astore 51
    //   748: aload_0
    //   749: invokespecial 424	com/alipay/android/phone/mrpc/core/q:e	()V
    //   752: aload_0
    //   753: getfield 77	com/alipay/android/phone/mrpc/core/q:c	Lcom/alipay/android/phone/mrpc/core/o;
    //   756: invokevirtual 277	com/alipay/android/phone/mrpc/core/o:f	()Lcom/alipay/android/phone/mrpc/core/ac;
    //   759: ifnull +29 -> 788
    //   762: aload_0
    //   763: getfield 77	com/alipay/android/phone/mrpc/core/q:c	Lcom/alipay/android/phone/mrpc/core/o;
    //   766: invokevirtual 277	com/alipay/android/phone/mrpc/core/o:f	()Lcom/alipay/android/phone/mrpc/core/ac;
    //   769: pop
    //   770: aload_0
    //   771: getfield 77	com/alipay/android/phone/mrpc/core/q:c	Lcom/alipay/android/phone/mrpc/core/o;
    //   774: pop
    //   775: new 122	java/lang/StringBuilder
    //   778: dup
    //   779: invokespecial 431	java/lang/StringBuilder:<init>	()V
    //   782: aload 51
    //   784: invokevirtual 434	java/lang/StringBuilder:append	(Ljava/lang/Object;)Ljava/lang/StringBuilder;
    //   787: pop
    //   788: new 122	java/lang/StringBuilder
    //   791: dup
    //   792: invokespecial 431	java/lang/StringBuilder:<init>	()V
    //   795: aload 51
    //   797: invokevirtual 434	java/lang/StringBuilder:append	(Ljava/lang/Object;)Ljava/lang/StringBuilder;
    //   800: pop
    //   801: new 375	com/alipay/android/phone/mrpc/core/HttpException
    //   804: dup
    //   805: iconst_2
    //   806: invokestatic 417	java/lang/Integer:valueOf	(I)Ljava/lang/Integer;
    //   809: aload 51
    //   811: invokestatic 614	java/lang/String:valueOf	(Ljava/lang/Object;)Ljava/lang/String;
    //   814: invokespecial 422	com/alipay/android/phone/mrpc/core/HttpException:<init>	(Ljava/lang/Integer;Ljava/lang/String;)V
    //   817: athrow
    //   818: aload_0
    //   819: invokespecial 559	com/alipay/android/phone/mrpc/core/q:h	()Ljava/net/URL;
    //   822: astore 76
    //   824: aload_0
    //   825: new 533	org/apache/http/HttpHost
    //   828: dup
    //   829: aload 76
    //   831: invokevirtual 564	java/net/URL:getHost	()Ljava/lang/String;
    //   834: aload_0
    //   835: invokespecial 556	com/alipay/android/phone/mrpc/core/q:g	()I
    //   838: aload 76
    //   840: invokevirtual 617	java/net/URL:getProtocol	()Ljava/lang/String;
    //   843: invokespecial 620	org/apache/http/HttpHost:<init>	(Ljava/lang/String;ILjava/lang/String;)V
    //   846: putfield 554	com/alipay/android/phone/mrpc/core/q:k	Lorg/apache/http/HttpHost;
    //   849: aload_0
    //   850: getfield 554	com/alipay/android/phone/mrpc/core/q:k	Lorg/apache/http/HttpHost;
    //   853: astore 77
    //   855: goto -354 -> 501
    //   858: aload_0
    //   859: getfield 77	com/alipay/android/phone/mrpc/core/q:c	Lcom/alipay/android/phone/mrpc/core/o;
    //   862: pop
    //   863: aload 78
    //   865: invokeinterface 149 1 0
    //   870: invokeinterface 155 1 0
    //   875: istore 83
    //   877: aload 78
    //   879: invokeinterface 149 1 0
    //   884: invokeinterface 623 1 0
    //   889: astore 84
    //   891: iload 83
    //   893: sipush 200
    //   896: if_icmpeq +132 -> 1028
    //   899: iload 83
    //   901: sipush 304
    //   904: if_icmpne +118 -> 1022
    //   907: iconst_1
    //   908: istore 94
    //   910: iload 94
    //   912: ifne +116 -> 1028
    //   915: new 375	com/alipay/android/phone/mrpc/core/HttpException
    //   918: dup
    //   919: aload 78
    //   921: invokeinterface 149 1 0
    //   926: invokeinterface 155 1 0
    //   931: invokestatic 417	java/lang/Integer:valueOf	(I)Ljava/lang/Integer;
    //   934: aload 78
    //   936: invokeinterface 149 1 0
    //   941: invokeinterface 623 1 0
    //   946: invokespecial 422	com/alipay/android/phone/mrpc/core/HttpException:<init>	(Ljava/lang/Integer;Ljava/lang/String;)V
    //   949: athrow
    //   950: astore 46
    //   952: aload_0
    //   953: invokespecial 424	com/alipay/android/phone/mrpc/core/q:e	()V
    //   956: aload_0
    //   957: getfield 77	com/alipay/android/phone/mrpc/core/q:c	Lcom/alipay/android/phone/mrpc/core/o;
    //   960: invokevirtual 277	com/alipay/android/phone/mrpc/core/o:f	()Lcom/alipay/android/phone/mrpc/core/ac;
    //   963: ifnull +29 -> 992
    //   966: aload_0
    //   967: getfield 77	com/alipay/android/phone/mrpc/core/q:c	Lcom/alipay/android/phone/mrpc/core/o;
    //   970: invokevirtual 277	com/alipay/android/phone/mrpc/core/o:f	()Lcom/alipay/android/phone/mrpc/core/ac;
    //   973: pop
    //   974: aload_0
    //   975: getfield 77	com/alipay/android/phone/mrpc/core/q:c	Lcom/alipay/android/phone/mrpc/core/o;
    //   978: pop
    //   979: new 122	java/lang/StringBuilder
    //   982: dup
    //   983: invokespecial 431	java/lang/StringBuilder:<init>	()V
    //   986: aload 46
    //   988: invokevirtual 434	java/lang/StringBuilder:append	(Ljava/lang/Object;)Ljava/lang/StringBuilder;
    //   991: pop
    //   992: new 122	java/lang/StringBuilder
    //   995: dup
    //   996: invokespecial 431	java/lang/StringBuilder:<init>	()V
    //   999: aload 46
    //   1001: invokevirtual 434	java/lang/StringBuilder:append	(Ljava/lang/Object;)Ljava/lang/StringBuilder;
    //   1004: pop
    //   1005: new 375	com/alipay/android/phone/mrpc/core/HttpException
    //   1008: dup
    //   1009: iconst_2
    //   1010: invokestatic 417	java/lang/Integer:valueOf	(I)Ljava/lang/Integer;
    //   1013: aload 46
    //   1015: invokestatic 614	java/lang/String:valueOf	(Ljava/lang/Object;)Ljava/lang/String;
    //   1018: invokespecial 422	com/alipay/android/phone/mrpc/core/HttpException:<init>	(Ljava/lang/Integer;Ljava/lang/String;)V
    //   1021: athrow
    //   1022: iconst_0
    //   1023: istore 94
    //   1025: goto -115 -> 910
    //   1028: aload_0
    //   1029: aload 78
    //   1031: iload 83
    //   1033: aload 84
    //   1035: invokespecial 625	com/alipay/android/phone/mrpc/core/q:a	(Lorg/apache/http/HttpResponse;ILjava/lang/String;)Lcom/alipay/android/phone/mrpc/core/u;
    //   1038: astore 85
    //   1040: ldc2_w 626
    //   1043: lstore 86
    //   1045: aload 85
    //   1047: ifnull +20 -> 1067
    //   1050: aload 85
    //   1052: invokevirtual 630	com/alipay/android/phone/mrpc/core/u:b	()[B
    //   1055: ifnull +12 -> 1067
    //   1058: aload 85
    //   1060: invokevirtual 630	com/alipay/android/phone/mrpc/core/u:b	()[B
    //   1063: arraylength
    //   1064: i2l
    //   1065: lstore 86
    //   1067: lload 86
    //   1069: ldc2_w 626
    //   1072: lcmp
    //   1073: ifne +33 -> 1106
    //   1076: aload 85
    //   1078: instanceof 184
    //   1081: ifeq +25 -> 1106
    //   1084: aload 85
    //   1086: checkcast 184	com/alipay/android/phone/mrpc/core/p
    //   1089: astore 90
    //   1091: aload 90
    //   1093: invokevirtual 633	com/alipay/android/phone/mrpc/core/p:a	()Lcom/alipay/android/phone/mrpc/core/HttpUrlHeader;
    //   1096: ldc_w 635
    //   1099: invokevirtual 638	com/alipay/android/phone/mrpc/core/HttpUrlHeader:getHead	(Ljava/lang/String;)Ljava/lang/String;
    //   1102: invokestatic 94	java/lang/Long:parseLong	(Ljava/lang/String;)J
    //   1105: pop2
    //   1106: aload_0
    //   1107: getfield 77	com/alipay/android/phone/mrpc/core/q:c	Lcom/alipay/android/phone/mrpc/core/o;
    //   1110: invokevirtual 315	com/alipay/android/phone/mrpc/core/o:a	()Ljava/lang/String;
    //   1113: astore 88
    //   1115: aload 88
    //   1117: ifnull +39 -> 1156
    //   1120: aload_0
    //   1121: invokespecial 509	com/alipay/android/phone/mrpc/core/q:f	()Ljava/lang/String;
    //   1124: invokestatic 641	android/text/TextUtils:isEmpty	(Ljava/lang/CharSequence;)Z
    //   1127: ifne +29 -> 1156
    //   1130: new 122	java/lang/StringBuilder
    //   1133: dup
    //   1134: invokespecial 431	java/lang/StringBuilder:<init>	()V
    //   1137: aload 88
    //   1139: invokevirtual 294	java/lang/StringBuilder:append	(Ljava/lang/String;)Ljava/lang/StringBuilder;
    //   1142: ldc_w 643
    //   1145: invokevirtual 294	java/lang/StringBuilder:append	(Ljava/lang/String;)Ljava/lang/StringBuilder;
    //   1148: aload_0
    //   1149: invokespecial 509	com/alipay/android/phone/mrpc/core/q:f	()Ljava/lang/String;
    //   1152: invokevirtual 294	java/lang/StringBuilder:append	(Ljava/lang/String;)Ljava/lang/StringBuilder;
    //   1155: pop
    //   1156: aload 85
    //   1158: areturn
    //   1159: astore 41
    //   1161: aload_0
    //   1162: invokespecial 424	com/alipay/android/phone/mrpc/core/q:e	()V
    //   1165: aload_0
    //   1166: getfield 77	com/alipay/android/phone/mrpc/core/q:c	Lcom/alipay/android/phone/mrpc/core/o;
    //   1169: invokevirtual 277	com/alipay/android/phone/mrpc/core/o:f	()Lcom/alipay/android/phone/mrpc/core/ac;
    //   1172: ifnull +29 -> 1201
    //   1175: aload_0
    //   1176: getfield 77	com/alipay/android/phone/mrpc/core/q:c	Lcom/alipay/android/phone/mrpc/core/o;
    //   1179: invokevirtual 277	com/alipay/android/phone/mrpc/core/o:f	()Lcom/alipay/android/phone/mrpc/core/ac;
    //   1182: pop
    //   1183: aload_0
    //   1184: getfield 77	com/alipay/android/phone/mrpc/core/q:c	Lcom/alipay/android/phone/mrpc/core/o;
    //   1187: pop
    //   1188: new 122	java/lang/StringBuilder
    //   1191: dup
    //   1192: invokespecial 431	java/lang/StringBuilder:<init>	()V
    //   1195: aload 41
    //   1197: invokevirtual 434	java/lang/StringBuilder:append	(Ljava/lang/Object;)Ljava/lang/StringBuilder;
    //   1200: pop
    //   1201: new 122	java/lang/StringBuilder
    //   1204: dup
    //   1205: invokespecial 431	java/lang/StringBuilder:<init>	()V
    //   1208: aload 41
    //   1210: invokevirtual 434	java/lang/StringBuilder:append	(Ljava/lang/Object;)Ljava/lang/StringBuilder;
    //   1213: pop
    //   1214: new 375	com/alipay/android/phone/mrpc/core/HttpException
    //   1217: dup
    //   1218: bipush 6
    //   1220: invokestatic 417	java/lang/Integer:valueOf	(I)Ljava/lang/Integer;
    //   1223: aload 41
    //   1225: invokestatic 614	java/lang/String:valueOf	(Ljava/lang/Object;)Ljava/lang/String;
    //   1228: invokespecial 422	com/alipay/android/phone/mrpc/core/HttpException:<init>	(Ljava/lang/Integer;Ljava/lang/String;)V
    //   1231: athrow
    //   1232: astore 36
    //   1234: aload_0
    //   1235: invokespecial 424	com/alipay/android/phone/mrpc/core/q:e	()V
    //   1238: aload_0
    //   1239: getfield 77	com/alipay/android/phone/mrpc/core/q:c	Lcom/alipay/android/phone/mrpc/core/o;
    //   1242: invokevirtual 277	com/alipay/android/phone/mrpc/core/o:f	()Lcom/alipay/android/phone/mrpc/core/ac;
    //   1245: ifnull +29 -> 1274
    //   1248: aload_0
    //   1249: getfield 77	com/alipay/android/phone/mrpc/core/q:c	Lcom/alipay/android/phone/mrpc/core/o;
    //   1252: invokevirtual 277	com/alipay/android/phone/mrpc/core/o:f	()Lcom/alipay/android/phone/mrpc/core/ac;
    //   1255: pop
    //   1256: aload_0
    //   1257: getfield 77	com/alipay/android/phone/mrpc/core/q:c	Lcom/alipay/android/phone/mrpc/core/o;
    //   1260: pop
    //   1261: new 122	java/lang/StringBuilder
    //   1264: dup
    //   1265: invokespecial 431	java/lang/StringBuilder:<init>	()V
    //   1268: aload 36
    //   1270: invokevirtual 434	java/lang/StringBuilder:append	(Ljava/lang/Object;)Ljava/lang/StringBuilder;
    //   1273: pop
    //   1274: new 122	java/lang/StringBuilder
    //   1277: dup
    //   1278: invokespecial 431	java/lang/StringBuilder:<init>	()V
    //   1281: aload 36
    //   1283: invokevirtual 434	java/lang/StringBuilder:append	(Ljava/lang/Object;)Ljava/lang/StringBuilder;
    //   1286: pop
    //   1287: new 375	com/alipay/android/phone/mrpc/core/HttpException
    //   1290: dup
    //   1291: iconst_3
    //   1292: invokestatic 417	java/lang/Integer:valueOf	(I)Ljava/lang/Integer;
    //   1295: aload 36
    //   1297: invokestatic 614	java/lang/String:valueOf	(Ljava/lang/Object;)Ljava/lang/String;
    //   1300: invokespecial 422	com/alipay/android/phone/mrpc/core/HttpException:<init>	(Ljava/lang/Integer;Ljava/lang/String;)V
    //   1303: athrow
    //   1304: astore 31
    //   1306: aload_0
    //   1307: invokespecial 424	com/alipay/android/phone/mrpc/core/q:e	()V
    //   1310: aload_0
    //   1311: getfield 77	com/alipay/android/phone/mrpc/core/q:c	Lcom/alipay/android/phone/mrpc/core/o;
    //   1314: invokevirtual 277	com/alipay/android/phone/mrpc/core/o:f	()Lcom/alipay/android/phone/mrpc/core/ac;
    //   1317: ifnull +29 -> 1346
    //   1320: aload_0
    //   1321: getfield 77	com/alipay/android/phone/mrpc/core/q:c	Lcom/alipay/android/phone/mrpc/core/o;
    //   1324: invokevirtual 277	com/alipay/android/phone/mrpc/core/o:f	()Lcom/alipay/android/phone/mrpc/core/ac;
    //   1327: pop
    //   1328: aload_0
    //   1329: getfield 77	com/alipay/android/phone/mrpc/core/q:c	Lcom/alipay/android/phone/mrpc/core/o;
    //   1332: pop
    //   1333: new 122	java/lang/StringBuilder
    //   1336: dup
    //   1337: invokespecial 431	java/lang/StringBuilder:<init>	()V
    //   1340: aload 31
    //   1342: invokevirtual 434	java/lang/StringBuilder:append	(Ljava/lang/Object;)Ljava/lang/StringBuilder;
    //   1345: pop
    //   1346: new 122	java/lang/StringBuilder
    //   1349: dup
    //   1350: invokespecial 431	java/lang/StringBuilder:<init>	()V
    //   1353: aload 31
    //   1355: invokevirtual 434	java/lang/StringBuilder:append	(Ljava/lang/Object;)Ljava/lang/StringBuilder;
    //   1358: pop
    //   1359: new 375	com/alipay/android/phone/mrpc/core/HttpException
    //   1362: dup
    //   1363: iconst_3
    //   1364: invokestatic 417	java/lang/Integer:valueOf	(I)Ljava/lang/Integer;
    //   1367: aload 31
    //   1369: invokestatic 614	java/lang/String:valueOf	(Ljava/lang/Object;)Ljava/lang/String;
    //   1372: invokespecial 422	com/alipay/android/phone/mrpc/core/HttpException:<init>	(Ljava/lang/Integer;Ljava/lang/String;)V
    //   1375: athrow
    //   1376: astore 26
    //   1378: aload_0
    //   1379: invokespecial 424	com/alipay/android/phone/mrpc/core/q:e	()V
    //   1382: aload_0
    //   1383: getfield 77	com/alipay/android/phone/mrpc/core/q:c	Lcom/alipay/android/phone/mrpc/core/o;
    //   1386: invokevirtual 277	com/alipay/android/phone/mrpc/core/o:f	()Lcom/alipay/android/phone/mrpc/core/ac;
    //   1389: ifnull +29 -> 1418
    //   1392: aload_0
    //   1393: getfield 77	com/alipay/android/phone/mrpc/core/q:c	Lcom/alipay/android/phone/mrpc/core/o;
    //   1396: invokevirtual 277	com/alipay/android/phone/mrpc/core/o:f	()Lcom/alipay/android/phone/mrpc/core/ac;
    //   1399: pop
    //   1400: aload_0
    //   1401: getfield 77	com/alipay/android/phone/mrpc/core/q:c	Lcom/alipay/android/phone/mrpc/core/o;
    //   1404: pop
    //   1405: new 122	java/lang/StringBuilder
    //   1408: dup
    //   1409: invokespecial 431	java/lang/StringBuilder:<init>	()V
    //   1412: aload 26
    //   1414: invokevirtual 434	java/lang/StringBuilder:append	(Ljava/lang/Object;)Ljava/lang/StringBuilder;
    //   1417: pop
    //   1418: new 122	java/lang/StringBuilder
    //   1421: dup
    //   1422: invokespecial 431	java/lang/StringBuilder:<init>	()V
    //   1425: aload 26
    //   1427: invokevirtual 434	java/lang/StringBuilder:append	(Ljava/lang/Object;)Ljava/lang/StringBuilder;
    //   1430: pop
    //   1431: new 375	com/alipay/android/phone/mrpc/core/HttpException
    //   1434: dup
    //   1435: iconst_4
    //   1436: invokestatic 417	java/lang/Integer:valueOf	(I)Ljava/lang/Integer;
    //   1439: aload 26
    //   1441: invokestatic 614	java/lang/String:valueOf	(Ljava/lang/Object;)Ljava/lang/String;
    //   1444: invokespecial 422	com/alipay/android/phone/mrpc/core/HttpException:<init>	(Ljava/lang/Integer;Ljava/lang/String;)V
    //   1447: athrow
    //   1448: astore 21
    //   1450: aload_0
    //   1451: invokespecial 424	com/alipay/android/phone/mrpc/core/q:e	()V
    //   1454: aload_0
    //   1455: getfield 77	com/alipay/android/phone/mrpc/core/q:c	Lcom/alipay/android/phone/mrpc/core/o;
    //   1458: invokevirtual 277	com/alipay/android/phone/mrpc/core/o:f	()Lcom/alipay/android/phone/mrpc/core/ac;
    //   1461: ifnull +29 -> 1490
    //   1464: aload_0
    //   1465: getfield 77	com/alipay/android/phone/mrpc/core/q:c	Lcom/alipay/android/phone/mrpc/core/o;
    //   1468: invokevirtual 277	com/alipay/android/phone/mrpc/core/o:f	()Lcom/alipay/android/phone/mrpc/core/ac;
    //   1471: pop
    //   1472: aload_0
    //   1473: getfield 77	com/alipay/android/phone/mrpc/core/q:c	Lcom/alipay/android/phone/mrpc/core/o;
    //   1476: pop
    //   1477: new 122	java/lang/StringBuilder
    //   1480: dup
    //   1481: invokespecial 431	java/lang/StringBuilder:<init>	()V
    //   1484: aload 21
    //   1486: invokevirtual 434	java/lang/StringBuilder:append	(Ljava/lang/Object;)Ljava/lang/StringBuilder;
    //   1489: pop
    //   1490: new 122	java/lang/StringBuilder
    //   1493: dup
    //   1494: invokespecial 431	java/lang/StringBuilder:<init>	()V
    //   1497: aload 21
    //   1499: invokevirtual 434	java/lang/StringBuilder:append	(Ljava/lang/Object;)Ljava/lang/StringBuilder;
    //   1502: pop
    //   1503: new 375	com/alipay/android/phone/mrpc/core/HttpException
    //   1506: dup
    //   1507: iconst_5
    //   1508: invokestatic 417	java/lang/Integer:valueOf	(I)Ljava/lang/Integer;
    //   1511: aload 21
    //   1513: invokestatic 614	java/lang/String:valueOf	(Ljava/lang/Object;)Ljava/lang/String;
    //   1516: invokespecial 422	com/alipay/android/phone/mrpc/core/HttpException:<init>	(Ljava/lang/Integer;Ljava/lang/String;)V
    //   1519: athrow
    //   1520: astore 17
    //   1522: aload_0
    //   1523: invokespecial 424	com/alipay/android/phone/mrpc/core/q:e	()V
    //   1526: aload_0
    //   1527: getfield 77	com/alipay/android/phone/mrpc/core/q:c	Lcom/alipay/android/phone/mrpc/core/o;
    //   1530: invokevirtual 277	com/alipay/android/phone/mrpc/core/o:f	()Lcom/alipay/android/phone/mrpc/core/ac;
    //   1533: ifnull +29 -> 1562
    //   1536: aload_0
    //   1537: getfield 77	com/alipay/android/phone/mrpc/core/q:c	Lcom/alipay/android/phone/mrpc/core/o;
    //   1540: invokevirtual 277	com/alipay/android/phone/mrpc/core/o:f	()Lcom/alipay/android/phone/mrpc/core/ac;
    //   1543: pop
    //   1544: aload_0
    //   1545: getfield 77	com/alipay/android/phone/mrpc/core/q:c	Lcom/alipay/android/phone/mrpc/core/o;
    //   1548: pop
    //   1549: new 122	java/lang/StringBuilder
    //   1552: dup
    //   1553: invokespecial 431	java/lang/StringBuilder:<init>	()V
    //   1556: aload 17
    //   1558: invokevirtual 434	java/lang/StringBuilder:append	(Ljava/lang/Object;)Ljava/lang/StringBuilder;
    //   1561: pop
    //   1562: new 375	com/alipay/android/phone/mrpc/core/HttpException
    //   1565: dup
    //   1566: bipush 8
    //   1568: invokestatic 417	java/lang/Integer:valueOf	(I)Ljava/lang/Integer;
    //   1571: aload 17
    //   1573: invokestatic 614	java/lang/String:valueOf	(Ljava/lang/Object;)Ljava/lang/String;
    //   1576: invokespecial 422	com/alipay/android/phone/mrpc/core/HttpException:<init>	(Ljava/lang/Integer;Ljava/lang/String;)V
    //   1579: athrow
    //   1580: astore 12
    //   1582: aload_0
    //   1583: invokespecial 424	com/alipay/android/phone/mrpc/core/q:e	()V
    //   1586: aload_0
    //   1587: getfield 77	com/alipay/android/phone/mrpc/core/q:c	Lcom/alipay/android/phone/mrpc/core/o;
    //   1590: invokevirtual 277	com/alipay/android/phone/mrpc/core/o:f	()Lcom/alipay/android/phone/mrpc/core/ac;
    //   1593: ifnull +29 -> 1622
    //   1596: aload_0
    //   1597: getfield 77	com/alipay/android/phone/mrpc/core/q:c	Lcom/alipay/android/phone/mrpc/core/o;
    //   1600: invokevirtual 277	com/alipay/android/phone/mrpc/core/o:f	()Lcom/alipay/android/phone/mrpc/core/ac;
    //   1603: pop
    //   1604: aload_0
    //   1605: getfield 77	com/alipay/android/phone/mrpc/core/q:c	Lcom/alipay/android/phone/mrpc/core/o;
    //   1608: pop
    //   1609: new 122	java/lang/StringBuilder
    //   1612: dup
    //   1613: invokespecial 431	java/lang/StringBuilder:<init>	()V
    //   1616: aload 12
    //   1618: invokevirtual 434	java/lang/StringBuilder:append	(Ljava/lang/Object;)Ljava/lang/StringBuilder;
    //   1621: pop
    //   1622: new 122	java/lang/StringBuilder
    //   1625: dup
    //   1626: invokespecial 431	java/lang/StringBuilder:<init>	()V
    //   1629: aload 12
    //   1631: invokevirtual 434	java/lang/StringBuilder:append	(Ljava/lang/Object;)Ljava/lang/StringBuilder;
    //   1634: pop
    //   1635: new 375	com/alipay/android/phone/mrpc/core/HttpException
    //   1638: dup
    //   1639: bipush 9
    //   1641: invokestatic 417	java/lang/Integer:valueOf	(I)Ljava/lang/Integer;
    //   1644: aload 12
    //   1646: invokestatic 614	java/lang/String:valueOf	(Ljava/lang/Object;)Ljava/lang/String;
    //   1649: invokespecial 422	com/alipay/android/phone/mrpc/core/HttpException:<init>	(Ljava/lang/Integer;Ljava/lang/String;)V
    //   1652: athrow
    //   1653: astore 7
    //   1655: aload_0
    //   1656: invokespecial 424	com/alipay/android/phone/mrpc/core/q:e	()V
    //   1659: aload_0
    //   1660: getfield 77	com/alipay/android/phone/mrpc/core/q:c	Lcom/alipay/android/phone/mrpc/core/o;
    //   1663: invokevirtual 277	com/alipay/android/phone/mrpc/core/o:f	()Lcom/alipay/android/phone/mrpc/core/ac;
    //   1666: ifnull +29 -> 1695
    //   1669: aload_0
    //   1670: getfield 77	com/alipay/android/phone/mrpc/core/q:c	Lcom/alipay/android/phone/mrpc/core/o;
    //   1673: invokevirtual 277	com/alipay/android/phone/mrpc/core/o:f	()Lcom/alipay/android/phone/mrpc/core/ac;
    //   1676: pop
    //   1677: aload_0
    //   1678: getfield 77	com/alipay/android/phone/mrpc/core/q:c	Lcom/alipay/android/phone/mrpc/core/o;
    //   1681: pop
    //   1682: new 122	java/lang/StringBuilder
    //   1685: dup
    //   1686: invokespecial 431	java/lang/StringBuilder:<init>	()V
    //   1689: aload 7
    //   1691: invokevirtual 434	java/lang/StringBuilder:append	(Ljava/lang/Object;)Ljava/lang/StringBuilder;
    //   1694: pop
    //   1695: new 122	java/lang/StringBuilder
    //   1698: dup
    //   1699: invokespecial 431	java/lang/StringBuilder:<init>	()V
    //   1702: aload 7
    //   1704: invokevirtual 434	java/lang/StringBuilder:append	(Ljava/lang/Object;)Ljava/lang/StringBuilder;
    //   1707: pop
    //   1708: new 375	com/alipay/android/phone/mrpc/core/HttpException
    //   1711: dup
    //   1712: bipush 6
    //   1714: invokestatic 417	java/lang/Integer:valueOf	(I)Ljava/lang/Integer;
    //   1717: aload 7
    //   1719: invokestatic 614	java/lang/String:valueOf	(Ljava/lang/Object;)Ljava/lang/String;
    //   1722: invokespecial 422	com/alipay/android/phone/mrpc/core/HttpException:<init>	(Ljava/lang/Integer;Ljava/lang/String;)V
    //   1725: athrow
    //   1726: astore 5
    //   1728: aload_0
    //   1729: invokespecial 424	com/alipay/android/phone/mrpc/core/q:e	()V
    //   1732: aload_0
    //   1733: getfield 61	com/alipay/android/phone/mrpc/core/q:m	I
    //   1736: ifgt +16 -> 1752
    //   1739: aload_0
    //   1740: iconst_1
    //   1741: aload_0
    //   1742: getfield 61	com/alipay/android/phone/mrpc/core/q:m	I
    //   1745: iadd
    //   1746: putfield 61	com/alipay/android/phone/mrpc/core/q:m	I
    //   1749: goto -1749 -> 0
    //   1752: new 122	java/lang/StringBuilder
    //   1755: dup
    //   1756: invokespecial 431	java/lang/StringBuilder:<init>	()V
    //   1759: aload 5
    //   1761: invokevirtual 434	java/lang/StringBuilder:append	(Ljava/lang/Object;)Ljava/lang/StringBuilder;
    //   1764: pop
    //   1765: new 375	com/alipay/android/phone/mrpc/core/HttpException
    //   1768: dup
    //   1769: iconst_0
    //   1770: invokestatic 417	java/lang/Integer:valueOf	(I)Ljava/lang/Integer;
    //   1773: aload 5
    //   1775: invokestatic 614	java/lang/String:valueOf	(Ljava/lang/Object;)Ljava/lang/String;
    //   1778: invokespecial 422	com/alipay/android/phone/mrpc/core/HttpException:<init>	(Ljava/lang/Integer;Ljava/lang/String;)V
    //   1781: athrow
    //   1782: astore_1
    //   1783: aload_0
    //   1784: invokespecial 424	com/alipay/android/phone/mrpc/core/q:e	()V
    //   1787: aload_0
    //   1788: getfield 77	com/alipay/android/phone/mrpc/core/q:c	Lcom/alipay/android/phone/mrpc/core/o;
    //   1791: invokevirtual 277	com/alipay/android/phone/mrpc/core/o:f	()Lcom/alipay/android/phone/mrpc/core/ac;
    //   1794: ifnull +28 -> 1822
    //   1797: aload_0
    //   1798: getfield 77	com/alipay/android/phone/mrpc/core/q:c	Lcom/alipay/android/phone/mrpc/core/o;
    //   1801: invokevirtual 277	com/alipay/android/phone/mrpc/core/o:f	()Lcom/alipay/android/phone/mrpc/core/ac;
    //   1804: pop
    //   1805: aload_0
    //   1806: getfield 77	com/alipay/android/phone/mrpc/core/q:c	Lcom/alipay/android/phone/mrpc/core/o;
    //   1809: pop
    //   1810: new 122	java/lang/StringBuilder
    //   1813: dup
    //   1814: invokespecial 431	java/lang/StringBuilder:<init>	()V
    //   1817: aload_1
    //   1818: invokevirtual 434	java/lang/StringBuilder:append	(Ljava/lang/Object;)Ljava/lang/StringBuilder;
    //   1821: pop
    //   1822: new 375	com/alipay/android/phone/mrpc/core/HttpException
    //   1825: dup
    //   1826: iconst_0
    //   1827: invokestatic 417	java/lang/Integer:valueOf	(I)Ljava/lang/Integer;
    //   1830: aload_1
    //   1831: invokestatic 614	java/lang/String:valueOf	(Ljava/lang/Object;)Ljava/lang/String;
    //   1834: invokespecial 422	com/alipay/android/phone/mrpc/core/HttpException:<init>	(Ljava/lang/Integer;Ljava/lang/String;)V
    //   1837: athrow
    //   1838: astore 91
    //   1840: goto -734 -> 1106
    //   1843: aconst_null
    //   1844: astore 74
    //   1846: goto -1404 -> 442
    //   1849: iconst_0
    //   1850: istore 67
    //   1852: goto -1826 -> 26
    //   1855: iinc 65 1
    //   1858: goto -1747 -> 111
    //   1861: ldc_w 645
    //   1864: astore 98
    //   1866: goto -1157 -> 709
    //
    // Exception table:
    //   from	to	target	type
    //   0	18	46	com/alipay/android/phone/mrpc/core/HttpException
    //   31	46	46	com/alipay/android/phone/mrpc/core/HttpException
    //   103	108	46	com/alipay/android/phone/mrpc/core/HttpException
    //   118	125	46	com/alipay/android/phone/mrpc/core/HttpException
    //   130	146	46	com/alipay/android/phone/mrpc/core/HttpException
    //   152	175	46	com/alipay/android/phone/mrpc/core/HttpException
    //   175	184	46	com/alipay/android/phone/mrpc/core/HttpException
    //   189	204	46	com/alipay/android/phone/mrpc/core/HttpException
    //   204	237	46	com/alipay/android/phone/mrpc/core/HttpException
    //   258	401	46	com/alipay/android/phone/mrpc/core/HttpException
    //   406	424	46	com/alipay/android/phone/mrpc/core/HttpException
    //   429	442	46	com/alipay/android/phone/mrpc/core/HttpException
    //   447	472	46	com/alipay/android/phone/mrpc/core/HttpException
    //   475	501	46	com/alipay/android/phone/mrpc/core/HttpException
    //   501	526	46	com/alipay/android/phone/mrpc/core/HttpException
    //   526	593	46	com/alipay/android/phone/mrpc/core/HttpException
    //   593	612	46	com/alipay/android/phone/mrpc/core/HttpException
    //   612	704	46	com/alipay/android/phone/mrpc/core/HttpException
    //   709	743	46	com/alipay/android/phone/mrpc/core/HttpException
    //   818	855	46	com/alipay/android/phone/mrpc/core/HttpException
    //   858	891	46	com/alipay/android/phone/mrpc/core/HttpException
    //   915	950	46	com/alipay/android/phone/mrpc/core/HttpException
    //   1028	1040	46	com/alipay/android/phone/mrpc/core/HttpException
    //   1050	1067	46	com/alipay/android/phone/mrpc/core/HttpException
    //   1076	1091	46	com/alipay/android/phone/mrpc/core/HttpException
    //   1091	1106	46	com/alipay/android/phone/mrpc/core/HttpException
    //   1106	1115	46	com/alipay/android/phone/mrpc/core/HttpException
    //   1120	1156	46	com/alipay/android/phone/mrpc/core/HttpException
    //   0	18	240	java/net/URISyntaxException
    //   31	46	240	java/net/URISyntaxException
    //   103	108	240	java/net/URISyntaxException
    //   118	125	240	java/net/URISyntaxException
    //   130	146	240	java/net/URISyntaxException
    //   152	175	240	java/net/URISyntaxException
    //   175	184	240	java/net/URISyntaxException
    //   189	204	240	java/net/URISyntaxException
    //   204	237	240	java/net/URISyntaxException
    //   258	401	240	java/net/URISyntaxException
    //   406	424	240	java/net/URISyntaxException
    //   429	442	240	java/net/URISyntaxException
    //   447	472	240	java/net/URISyntaxException
    //   475	501	240	java/net/URISyntaxException
    //   501	526	240	java/net/URISyntaxException
    //   526	593	240	java/net/URISyntaxException
    //   593	612	240	java/net/URISyntaxException
    //   612	704	240	java/net/URISyntaxException
    //   709	743	240	java/net/URISyntaxException
    //   818	855	240	java/net/URISyntaxException
    //   858	891	240	java/net/URISyntaxException
    //   915	950	240	java/net/URISyntaxException
    //   1028	1040	240	java/net/URISyntaxException
    //   1050	1067	240	java/net/URISyntaxException
    //   1076	1091	240	java/net/URISyntaxException
    //   1091	1106	240	java/net/URISyntaxException
    //   1106	1115	240	java/net/URISyntaxException
    //   1120	1156	240	java/net/URISyntaxException
    //   0	18	746	javax/net/ssl/SSLHandshakeException
    //   31	46	746	javax/net/ssl/SSLHandshakeException
    //   103	108	746	javax/net/ssl/SSLHandshakeException
    //   118	125	746	javax/net/ssl/SSLHandshakeException
    //   130	146	746	javax/net/ssl/SSLHandshakeException
    //   152	175	746	javax/net/ssl/SSLHandshakeException
    //   175	184	746	javax/net/ssl/SSLHandshakeException
    //   189	204	746	javax/net/ssl/SSLHandshakeException
    //   204	237	746	javax/net/ssl/SSLHandshakeException
    //   258	401	746	javax/net/ssl/SSLHandshakeException
    //   406	424	746	javax/net/ssl/SSLHandshakeException
    //   429	442	746	javax/net/ssl/SSLHandshakeException
    //   447	472	746	javax/net/ssl/SSLHandshakeException
    //   475	501	746	javax/net/ssl/SSLHandshakeException
    //   501	526	746	javax/net/ssl/SSLHandshakeException
    //   526	593	746	javax/net/ssl/SSLHandshakeException
    //   593	612	746	javax/net/ssl/SSLHandshakeException
    //   612	704	746	javax/net/ssl/SSLHandshakeException
    //   709	743	746	javax/net/ssl/SSLHandshakeException
    //   818	855	746	javax/net/ssl/SSLHandshakeException
    //   858	891	746	javax/net/ssl/SSLHandshakeException
    //   915	950	746	javax/net/ssl/SSLHandshakeException
    //   1028	1040	746	javax/net/ssl/SSLHandshakeException
    //   1050	1067	746	javax/net/ssl/SSLHandshakeException
    //   1076	1091	746	javax/net/ssl/SSLHandshakeException
    //   1091	1106	746	javax/net/ssl/SSLHandshakeException
    //   1106	1115	746	javax/net/ssl/SSLHandshakeException
    //   1120	1156	746	javax/net/ssl/SSLHandshakeException
    //   0	18	950	javax/net/ssl/SSLPeerUnverifiedException
    //   31	46	950	javax/net/ssl/SSLPeerUnverifiedException
    //   103	108	950	javax/net/ssl/SSLPeerUnverifiedException
    //   118	125	950	javax/net/ssl/SSLPeerUnverifiedException
    //   130	146	950	javax/net/ssl/SSLPeerUnverifiedException
    //   152	175	950	javax/net/ssl/SSLPeerUnverifiedException
    //   175	184	950	javax/net/ssl/SSLPeerUnverifiedException
    //   189	204	950	javax/net/ssl/SSLPeerUnverifiedException
    //   204	237	950	javax/net/ssl/SSLPeerUnverifiedException
    //   258	401	950	javax/net/ssl/SSLPeerUnverifiedException
    //   406	424	950	javax/net/ssl/SSLPeerUnverifiedException
    //   429	442	950	javax/net/ssl/SSLPeerUnverifiedException
    //   447	472	950	javax/net/ssl/SSLPeerUnverifiedException
    //   475	501	950	javax/net/ssl/SSLPeerUnverifiedException
    //   501	526	950	javax/net/ssl/SSLPeerUnverifiedException
    //   526	593	950	javax/net/ssl/SSLPeerUnverifiedException
    //   593	612	950	javax/net/ssl/SSLPeerUnverifiedException
    //   612	704	950	javax/net/ssl/SSLPeerUnverifiedException
    //   709	743	950	javax/net/ssl/SSLPeerUnverifiedException
    //   818	855	950	javax/net/ssl/SSLPeerUnverifiedException
    //   858	891	950	javax/net/ssl/SSLPeerUnverifiedException
    //   915	950	950	javax/net/ssl/SSLPeerUnverifiedException
    //   1028	1040	950	javax/net/ssl/SSLPeerUnverifiedException
    //   1050	1067	950	javax/net/ssl/SSLPeerUnverifiedException
    //   1076	1091	950	javax/net/ssl/SSLPeerUnverifiedException
    //   1091	1106	950	javax/net/ssl/SSLPeerUnverifiedException
    //   1106	1115	950	javax/net/ssl/SSLPeerUnverifiedException
    //   1120	1156	950	javax/net/ssl/SSLPeerUnverifiedException
    //   0	18	1159	javax/net/ssl/SSLException
    //   31	46	1159	javax/net/ssl/SSLException
    //   103	108	1159	javax/net/ssl/SSLException
    //   118	125	1159	javax/net/ssl/SSLException
    //   130	146	1159	javax/net/ssl/SSLException
    //   152	175	1159	javax/net/ssl/SSLException
    //   175	184	1159	javax/net/ssl/SSLException
    //   189	204	1159	javax/net/ssl/SSLException
    //   204	237	1159	javax/net/ssl/SSLException
    //   258	401	1159	javax/net/ssl/SSLException
    //   406	424	1159	javax/net/ssl/SSLException
    //   429	442	1159	javax/net/ssl/SSLException
    //   447	472	1159	javax/net/ssl/SSLException
    //   475	501	1159	javax/net/ssl/SSLException
    //   501	526	1159	javax/net/ssl/SSLException
    //   526	593	1159	javax/net/ssl/SSLException
    //   593	612	1159	javax/net/ssl/SSLException
    //   612	704	1159	javax/net/ssl/SSLException
    //   709	743	1159	javax/net/ssl/SSLException
    //   818	855	1159	javax/net/ssl/SSLException
    //   858	891	1159	javax/net/ssl/SSLException
    //   915	950	1159	javax/net/ssl/SSLException
    //   1028	1040	1159	javax/net/ssl/SSLException
    //   1050	1067	1159	javax/net/ssl/SSLException
    //   1076	1091	1159	javax/net/ssl/SSLException
    //   1091	1106	1159	javax/net/ssl/SSLException
    //   1106	1115	1159	javax/net/ssl/SSLException
    //   1120	1156	1159	javax/net/ssl/SSLException
    //   0	18	1232	org/apache/http/conn/ConnectionPoolTimeoutException
    //   31	46	1232	org/apache/http/conn/ConnectionPoolTimeoutException
    //   103	108	1232	org/apache/http/conn/ConnectionPoolTimeoutException
    //   118	125	1232	org/apache/http/conn/ConnectionPoolTimeoutException
    //   130	146	1232	org/apache/http/conn/ConnectionPoolTimeoutException
    //   152	175	1232	org/apache/http/conn/ConnectionPoolTimeoutException
    //   175	184	1232	org/apache/http/conn/ConnectionPoolTimeoutException
    //   189	204	1232	org/apache/http/conn/ConnectionPoolTimeoutException
    //   204	237	1232	org/apache/http/conn/ConnectionPoolTimeoutException
    //   258	401	1232	org/apache/http/conn/ConnectionPoolTimeoutException
    //   406	424	1232	org/apache/http/conn/ConnectionPoolTimeoutException
    //   429	442	1232	org/apache/http/conn/ConnectionPoolTimeoutException
    //   447	472	1232	org/apache/http/conn/ConnectionPoolTimeoutException
    //   475	501	1232	org/apache/http/conn/ConnectionPoolTimeoutException
    //   501	526	1232	org/apache/http/conn/ConnectionPoolTimeoutException
    //   526	593	1232	org/apache/http/conn/ConnectionPoolTimeoutException
    //   593	612	1232	org/apache/http/conn/ConnectionPoolTimeoutException
    //   612	704	1232	org/apache/http/conn/ConnectionPoolTimeoutException
    //   709	743	1232	org/apache/http/conn/ConnectionPoolTimeoutException
    //   818	855	1232	org/apache/http/conn/ConnectionPoolTimeoutException
    //   858	891	1232	org/apache/http/conn/ConnectionPoolTimeoutException
    //   915	950	1232	org/apache/http/conn/ConnectionPoolTimeoutException
    //   1028	1040	1232	org/apache/http/conn/ConnectionPoolTimeoutException
    //   1050	1067	1232	org/apache/http/conn/ConnectionPoolTimeoutException
    //   1076	1091	1232	org/apache/http/conn/ConnectionPoolTimeoutException
    //   1091	1106	1232	org/apache/http/conn/ConnectionPoolTimeoutException
    //   1106	1115	1232	org/apache/http/conn/ConnectionPoolTimeoutException
    //   1120	1156	1232	org/apache/http/conn/ConnectionPoolTimeoutException
    //   0	18	1304	org/apache/http/conn/ConnectTimeoutException
    //   31	46	1304	org/apache/http/conn/ConnectTimeoutException
    //   103	108	1304	org/apache/http/conn/ConnectTimeoutException
    //   118	125	1304	org/apache/http/conn/ConnectTimeoutException
    //   130	146	1304	org/apache/http/conn/ConnectTimeoutException
    //   152	175	1304	org/apache/http/conn/ConnectTimeoutException
    //   175	184	1304	org/apache/http/conn/ConnectTimeoutException
    //   189	204	1304	org/apache/http/conn/ConnectTimeoutException
    //   204	237	1304	org/apache/http/conn/ConnectTimeoutException
    //   258	401	1304	org/apache/http/conn/ConnectTimeoutException
    //   406	424	1304	org/apache/http/conn/ConnectTimeoutException
    //   429	442	1304	org/apache/http/conn/ConnectTimeoutException
    //   447	472	1304	org/apache/http/conn/ConnectTimeoutException
    //   475	501	1304	org/apache/http/conn/ConnectTimeoutException
    //   501	526	1304	org/apache/http/conn/ConnectTimeoutException
    //   526	593	1304	org/apache/http/conn/ConnectTimeoutException
    //   593	612	1304	org/apache/http/conn/ConnectTimeoutException
    //   612	704	1304	org/apache/http/conn/ConnectTimeoutException
    //   709	743	1304	org/apache/http/conn/ConnectTimeoutException
    //   818	855	1304	org/apache/http/conn/ConnectTimeoutException
    //   858	891	1304	org/apache/http/conn/ConnectTimeoutException
    //   915	950	1304	org/apache/http/conn/ConnectTimeoutException
    //   1028	1040	1304	org/apache/http/conn/ConnectTimeoutException
    //   1050	1067	1304	org/apache/http/conn/ConnectTimeoutException
    //   1076	1091	1304	org/apache/http/conn/ConnectTimeoutException
    //   1091	1106	1304	org/apache/http/conn/ConnectTimeoutException
    //   1106	1115	1304	org/apache/http/conn/ConnectTimeoutException
    //   1120	1156	1304	org/apache/http/conn/ConnectTimeoutException
    //   0	18	1376	java/net/SocketTimeoutException
    //   31	46	1376	java/net/SocketTimeoutException
    //   103	108	1376	java/net/SocketTimeoutException
    //   118	125	1376	java/net/SocketTimeoutException
    //   130	146	1376	java/net/SocketTimeoutException
    //   152	175	1376	java/net/SocketTimeoutException
    //   175	184	1376	java/net/SocketTimeoutException
    //   189	204	1376	java/net/SocketTimeoutException
    //   204	237	1376	java/net/SocketTimeoutException
    //   258	401	1376	java/net/SocketTimeoutException
    //   406	424	1376	java/net/SocketTimeoutException
    //   429	442	1376	java/net/SocketTimeoutException
    //   447	472	1376	java/net/SocketTimeoutException
    //   475	501	1376	java/net/SocketTimeoutException
    //   501	526	1376	java/net/SocketTimeoutException
    //   526	593	1376	java/net/SocketTimeoutException
    //   593	612	1376	java/net/SocketTimeoutException
    //   612	704	1376	java/net/SocketTimeoutException
    //   709	743	1376	java/net/SocketTimeoutException
    //   818	855	1376	java/net/SocketTimeoutException
    //   858	891	1376	java/net/SocketTimeoutException
    //   915	950	1376	java/net/SocketTimeoutException
    //   1028	1040	1376	java/net/SocketTimeoutException
    //   1050	1067	1376	java/net/SocketTimeoutException
    //   1076	1091	1376	java/net/SocketTimeoutException
    //   1091	1106	1376	java/net/SocketTimeoutException
    //   1106	1115	1376	java/net/SocketTimeoutException
    //   1120	1156	1376	java/net/SocketTimeoutException
    //   0	18	1448	org/apache/http/NoHttpResponseException
    //   31	46	1448	org/apache/http/NoHttpResponseException
    //   103	108	1448	org/apache/http/NoHttpResponseException
    //   118	125	1448	org/apache/http/NoHttpResponseException
    //   130	146	1448	org/apache/http/NoHttpResponseException
    //   152	175	1448	org/apache/http/NoHttpResponseException
    //   175	184	1448	org/apache/http/NoHttpResponseException
    //   189	204	1448	org/apache/http/NoHttpResponseException
    //   204	237	1448	org/apache/http/NoHttpResponseException
    //   258	401	1448	org/apache/http/NoHttpResponseException
    //   406	424	1448	org/apache/http/NoHttpResponseException
    //   429	442	1448	org/apache/http/NoHttpResponseException
    //   447	472	1448	org/apache/http/NoHttpResponseException
    //   475	501	1448	org/apache/http/NoHttpResponseException
    //   501	526	1448	org/apache/http/NoHttpResponseException
    //   526	593	1448	org/apache/http/NoHttpResponseException
    //   593	612	1448	org/apache/http/NoHttpResponseException
    //   612	704	1448	org/apache/http/NoHttpResponseException
    //   709	743	1448	org/apache/http/NoHttpResponseException
    //   818	855	1448	org/apache/http/NoHttpResponseException
    //   858	891	1448	org/apache/http/NoHttpResponseException
    //   915	950	1448	org/apache/http/NoHttpResponseException
    //   1028	1040	1448	org/apache/http/NoHttpResponseException
    //   1050	1067	1448	org/apache/http/NoHttpResponseException
    //   1076	1091	1448	org/apache/http/NoHttpResponseException
    //   1091	1106	1448	org/apache/http/NoHttpResponseException
    //   1106	1115	1448	org/apache/http/NoHttpResponseException
    //   1120	1156	1448	org/apache/http/NoHttpResponseException
    //   0	18	1520	org/apache/http/conn/HttpHostConnectException
    //   31	46	1520	org/apache/http/conn/HttpHostConnectException
    //   103	108	1520	org/apache/http/conn/HttpHostConnectException
    //   118	125	1520	org/apache/http/conn/HttpHostConnectException
    //   130	146	1520	org/apache/http/conn/HttpHostConnectException
    //   152	175	1520	org/apache/http/conn/HttpHostConnectException
    //   175	184	1520	org/apache/http/conn/HttpHostConnectException
    //   189	204	1520	org/apache/http/conn/HttpHostConnectException
    //   204	237	1520	org/apache/http/conn/HttpHostConnectException
    //   258	401	1520	org/apache/http/conn/HttpHostConnectException
    //   406	424	1520	org/apache/http/conn/HttpHostConnectException
    //   429	442	1520	org/apache/http/conn/HttpHostConnectException
    //   447	472	1520	org/apache/http/conn/HttpHostConnectException
    //   475	501	1520	org/apache/http/conn/HttpHostConnectException
    //   501	526	1520	org/apache/http/conn/HttpHostConnectException
    //   526	593	1520	org/apache/http/conn/HttpHostConnectException
    //   593	612	1520	org/apache/http/conn/HttpHostConnectException
    //   612	704	1520	org/apache/http/conn/HttpHostConnectException
    //   709	743	1520	org/apache/http/conn/HttpHostConnectException
    //   818	855	1520	org/apache/http/conn/HttpHostConnectException
    //   858	891	1520	org/apache/http/conn/HttpHostConnectException
    //   915	950	1520	org/apache/http/conn/HttpHostConnectException
    //   1028	1040	1520	org/apache/http/conn/HttpHostConnectException
    //   1050	1067	1520	org/apache/http/conn/HttpHostConnectException
    //   1076	1091	1520	org/apache/http/conn/HttpHostConnectException
    //   1091	1106	1520	org/apache/http/conn/HttpHostConnectException
    //   1106	1115	1520	org/apache/http/conn/HttpHostConnectException
    //   1120	1156	1520	org/apache/http/conn/HttpHostConnectException
    //   0	18	1580	java/net/UnknownHostException
    //   31	46	1580	java/net/UnknownHostException
    //   103	108	1580	java/net/UnknownHostException
    //   118	125	1580	java/net/UnknownHostException
    //   130	146	1580	java/net/UnknownHostException
    //   152	175	1580	java/net/UnknownHostException
    //   175	184	1580	java/net/UnknownHostException
    //   189	204	1580	java/net/UnknownHostException
    //   204	237	1580	java/net/UnknownHostException
    //   258	401	1580	java/net/UnknownHostException
    //   406	424	1580	java/net/UnknownHostException
    //   429	442	1580	java/net/UnknownHostException
    //   447	472	1580	java/net/UnknownHostException
    //   475	501	1580	java/net/UnknownHostException
    //   501	526	1580	java/net/UnknownHostException
    //   526	593	1580	java/net/UnknownHostException
    //   593	612	1580	java/net/UnknownHostException
    //   612	704	1580	java/net/UnknownHostException
    //   709	743	1580	java/net/UnknownHostException
    //   818	855	1580	java/net/UnknownHostException
    //   858	891	1580	java/net/UnknownHostException
    //   915	950	1580	java/net/UnknownHostException
    //   1028	1040	1580	java/net/UnknownHostException
    //   1050	1067	1580	java/net/UnknownHostException
    //   1076	1091	1580	java/net/UnknownHostException
    //   1091	1106	1580	java/net/UnknownHostException
    //   1106	1115	1580	java/net/UnknownHostException
    //   1120	1156	1580	java/net/UnknownHostException
    //   0	18	1653	java/io/IOException
    //   31	46	1653	java/io/IOException
    //   103	108	1653	java/io/IOException
    //   118	125	1653	java/io/IOException
    //   130	146	1653	java/io/IOException
    //   152	175	1653	java/io/IOException
    //   175	184	1653	java/io/IOException
    //   189	204	1653	java/io/IOException
    //   204	237	1653	java/io/IOException
    //   258	401	1653	java/io/IOException
    //   406	424	1653	java/io/IOException
    //   429	442	1653	java/io/IOException
    //   447	472	1653	java/io/IOException
    //   475	501	1653	java/io/IOException
    //   501	526	1653	java/io/IOException
    //   526	593	1653	java/io/IOException
    //   593	612	1653	java/io/IOException
    //   612	704	1653	java/io/IOException
    //   709	743	1653	java/io/IOException
    //   818	855	1653	java/io/IOException
    //   858	891	1653	java/io/IOException
    //   915	950	1653	java/io/IOException
    //   1028	1040	1653	java/io/IOException
    //   1050	1067	1653	java/io/IOException
    //   1076	1091	1653	java/io/IOException
    //   1091	1106	1653	java/io/IOException
    //   1106	1115	1653	java/io/IOException
    //   1120	1156	1653	java/io/IOException
    //   0	18	1726	java/lang/NullPointerException
    //   31	46	1726	java/lang/NullPointerException
    //   103	108	1726	java/lang/NullPointerException
    //   118	125	1726	java/lang/NullPointerException
    //   130	146	1726	java/lang/NullPointerException
    //   152	175	1726	java/lang/NullPointerException
    //   175	184	1726	java/lang/NullPointerException
    //   189	204	1726	java/lang/NullPointerException
    //   204	237	1726	java/lang/NullPointerException
    //   258	401	1726	java/lang/NullPointerException
    //   406	424	1726	java/lang/NullPointerException
    //   429	442	1726	java/lang/NullPointerException
    //   447	472	1726	java/lang/NullPointerException
    //   475	501	1726	java/lang/NullPointerException
    //   501	526	1726	java/lang/NullPointerException
    //   526	593	1726	java/lang/NullPointerException
    //   593	612	1726	java/lang/NullPointerException
    //   612	704	1726	java/lang/NullPointerException
    //   709	743	1726	java/lang/NullPointerException
    //   818	855	1726	java/lang/NullPointerException
    //   858	891	1726	java/lang/NullPointerException
    //   915	950	1726	java/lang/NullPointerException
    //   1028	1040	1726	java/lang/NullPointerException
    //   1050	1067	1726	java/lang/NullPointerException
    //   1076	1091	1726	java/lang/NullPointerException
    //   1091	1106	1726	java/lang/NullPointerException
    //   1106	1115	1726	java/lang/NullPointerException
    //   1120	1156	1726	java/lang/NullPointerException
    //   0	18	1782	java/lang/Exception
    //   31	46	1782	java/lang/Exception
    //   103	108	1782	java/lang/Exception
    //   118	125	1782	java/lang/Exception
    //   130	146	1782	java/lang/Exception
    //   152	175	1782	java/lang/Exception
    //   175	184	1782	java/lang/Exception
    //   189	204	1782	java/lang/Exception
    //   204	237	1782	java/lang/Exception
    //   258	401	1782	java/lang/Exception
    //   406	424	1782	java/lang/Exception
    //   429	442	1782	java/lang/Exception
    //   447	472	1782	java/lang/Exception
    //   475	501	1782	java/lang/Exception
    //   501	526	1782	java/lang/Exception
    //   526	593	1782	java/lang/Exception
    //   593	612	1782	java/lang/Exception
    //   612	704	1782	java/lang/Exception
    //   709	743	1782	java/lang/Exception
    //   818	855	1782	java/lang/Exception
    //   858	891	1782	java/lang/Exception
    //   915	950	1782	java/lang/Exception
    //   1028	1040	1782	java/lang/Exception
    //   1050	1067	1782	java/lang/Exception
    //   1076	1091	1782	java/lang/Exception
    //   1106	1115	1782	java/lang/Exception
    //   1120	1156	1782	java/lang/Exception
    //   1091	1106	1838	java/lang/Exception
  }

  private void e()
  {
    if (this.f != null)
      this.f.abort();
  }

  private String f()
  {
    if (!TextUtils.isEmpty(this.q))
      return this.q;
    this.q = this.c.b("operationType");
    return this.q;
  }

  private int g()
  {
    URL localURL = h();
    if (localURL.getPort() == -1)
      return localURL.getDefaultPort();
    return localURL.getPort();
  }

  private URL h()
  {
    if (this.l != null)
      return this.l;
    this.l = new URL(this.c.a());
    return this.l;
  }

  private CookieManager i()
  {
    if (this.i != null)
      return this.i;
    this.i = CookieManager.getInstance();
    return this.i;
  }

  public final o a()
  {
    return this.c;
  }
}

/* Location:           C:\Androidnixiangzhushou\zikao_classes_dex2jar.jar
 * Qualified Name:     com.alipay.android.phone.mrpc.core.q
 * JD-Core Version:    0.6.0
 */